{
    "seed": 119836516,
    "starttime": "2026-01-19_18-22-39",
    "endtime": "2026-01-19_18-22-39",
    "time_taken": "0:00:00.323610",
    "H_info": {
        "potential": "linear",
        "boundary_condition": "dirichlet",
        "cutoff": 16,
        "N": 2,
        "a": 1.0,
        "c": null,
        "num_qubits": 10,
        "num_paulis": 81,
        "keep_ratio": 0.999,
        "trunc_info": {
            "m": 64,
            "n": 81,
            "keep_frac_terms": 0.7901234567901234,
            "keep_ratio": 0.999,
            "truncated": 0.0003077278033742914,
            "total_weight": 330.78125
        },
        "dense_H_size": [
            1024,
            1024
        ],
        "eigenvalues": [
            5.822697273908591e-16,
            1.1180339887498802,
            1.1180339887498836,
            1.1180339887498845,
            1.118033988749896,
            2.2360679774997574,
            2.236067977499761,
            2.2360679774997623
        ],
        "basis": [
            0,
            0,
            0,
            0,
            0,
            0,
            0,
            0,
            0,
            1
        ]
    },
    "backend_info": {
        "backend_name": "Aer",
        "use_noise_model": 0,
        "noise_model_options": {
            "gate_error": true,
            "readout_error": true,
            "thermal_relaxation": true
        },
        "resilience_level": 2,
        "optimization_level": 3,
        "shots": 10000,
        "tags": [
            "NQCC-Q4",
            "SBQKD",
            "shots:10000",
            "dirichlet",
            "linear",
            "N=2",
            "cutoff=16"
        ]
    },
    "Ansatz_info": {
        "include_basis": true,
        "include_rys": true,
        "include_xxyys": true
    },
    "run_info": {
        "dt": 3.0,
        "max_k": 40,
        "tol": 1e-08,
        "conserve_fermion": true,
        "fermion_qubits": [
            4,
            9
        ],
        "num_fermions": 1,
        "trotter_patience": 2,
        "energy_patience": 3,
        "max_n_steps": 3
    },
    "final_k": 5,
    "converged": true,
    "all_energies": [
        1.2027655643014373e-07,
        7.623927006882406e-13,
        6.977486250819185e-15,
        -1.681011143108399e-14,
        -1.288407446743418e-14
    ],
    "all_run_data": [
        {
            "D": 1,
            "t": 3.0,
            "num_trotter_steps": 1,
            "circuit_time": "0:00:00.024492",
            "shot_processing": {
                "raw_unique_basis_states": 46,
                "fermion_basis_rejected": 0,
                "kept_unique_basis_states": 46,
                "fermion_shots_rejected": 0,
                "kept_shots": 10000
            },
            "new_basis_count": 46,
            "total_basis_count": 46,
            "H_reduced_size": [
                46,
                46
            ],
            "reduction": 95.5078125,
            "H_reduced_e": 1.2027655643014373e-07,
            "used_dense": true,
            "eigenvalue_time": "0:00:00.000492",
            "diff": 1.20276555847874e-07,
            "change_from_prev": null,
            "circuit_cost": {
                "depth": 100,
                "size": 219,
                "num_2q_ops": 136,
                "count_ops": {
                    "cx": 104,
                    "rz": 31,
                    "u2": 21,
                    "rzz": 12,
                    "unitary": 10,
                    "measure": 10,
                    "h": 7,
                    "rzx": 6,
                    "sxdg": 5,
                    "u3": 4,
                    "sx": 3,
                    "rx": 2,
                    "rxx": 2,
                    "ryy": 2,
                    "barrier": 1
                }
            }
        },
        {
            "D": 2,
            "t": 6.0,
            "num_trotter_steps": 1,
            "circuit_time": "0:00:00.030357",
            "shot_processing": {
                "raw_unique_basis_states": 45,
                "fermion_basis_rejected": 0,
                "kept_unique_basis_states": 45,
                "fermion_shots_rejected": 0,
                "kept_shots": 10000
            },
            "new_basis_count": 17,
            "total_basis_count": 63,
            "H_reduced_size": [
                63,
                63
            ],
            "reduction": 93.84765625,
            "H_reduced_e": 7.623927006882406e-13,
            "used_dense": true,
            "eigenvalue_time": "0:00:00.001175",
            "diff": 7.618104309608498e-13,
            "change_from_prev": 1.2027579403744304e-07,
            "circuit_cost": {
                "depth": 100,
                "size": 219,
                "num_2q_ops": 136,
                "count_ops": {
                    "cx": 104,
                    "rz": 31,
                    "u2": 21,
                    "rzz": 12,
                    "unitary": 10,
                    "measure": 10,
                    "h": 7,
                    "rzx": 6,
                    "sxdg": 5,
                    "u3": 4,
                    "sx": 3,
                    "rx": 2,
                    "rxx": 2,
                    "ryy": 2,
                    "barrier": 1
                }
            }
        },
        {
            "D": 3,
            "t": 9.0,
            "num_trotter_steps": 1,
            "circuit_time": "0:00:00.025736",
            "shot_processing": {
                "raw_unique_basis_states": 68,
                "fermion_basis_rejected": 0,
                "kept_unique_basis_states": 68,
                "fermion_shots_rejected": 0,
                "kept_shots": 10000
            },
            "new_basis_count": 26,
            "total_basis_count": 89,
            "H_reduced_size": [
                89,
                89
            ],
            "reduction": 91.30859375,
            "H_reduced_e": 6.977486250819185e-15,
            "used_dense": true,
            "eigenvalue_time": "0:00:00.002529",
            "diff": 6.395216523428326e-15,
            "change_from_prev": 7.554152144374215e-13,
            "circuit_cost": {
                "depth": 100,
                "size": 219,
                "num_2q_ops": 136,
                "count_ops": {
                    "cx": 104,
                    "rz": 31,
                    "u2": 21,
                    "rzz": 12,
                    "unitary": 10,
                    "measure": 10,
                    "h": 7,
                    "rzx": 6,
                    "sxdg": 5,
                    "u3": 4,
                    "sx": 3,
                    "rx": 2,
                    "rxx": 2,
                    "ryy": 2,
                    "barrier": 1
                }
            }
        },
        {
            "D": 4,
            "t": 12.0,
            "num_trotter_steps": 1,
            "circuit_time": "0:00:00.029684",
            "shot_processing": {
                "raw_unique_basis_states": 26,
                "fermion_basis_rejected": 0,
                "kept_unique_basis_states": 26,
                "fermion_shots_rejected": 0,
                "kept_shots": 10000
            },
            "new_basis_count": 4,
            "total_basis_count": 93,
            "H_reduced_size": [
                93,
                93
            ],
            "reduction": 90.91796875,
            "H_reduced_e": -1.681011143108399e-14,
            "used_dense": true,
            "eigenvalue_time": "0:00:00.002621",
            "diff": 1.739238115847485e-14,
            "change_from_prev": 2.3787597681903176e-14,
            "circuit_cost": {
                "depth": 100,
                "size": 219,
                "num_2q_ops": 136,
                "count_ops": {
                    "cx": 104,
                    "rz": 31,
                    "u2": 21,
                    "rzz": 12,
                    "unitary": 10,
                    "measure": 10,
                    "h": 7,
                    "rzx": 6,
                    "sxdg": 5,
                    "u3": 4,
                    "sx": 3,
                    "rx": 2,
                    "rxx": 2,
                    "ryy": 2,
                    "barrier": 1
                }
            }
        },
        {
            "D": 5,
            "t": 7.5,
            "num_trotter_steps": 2,
            "circuit_time": "0:00:00.032612",
            "shot_processing": {
                "raw_unique_basis_states": 97,
                "fermion_basis_rejected": 0,
                "kept_unique_basis_states": 97,
                "fermion_shots_rejected": 0,
                "kept_shots": 10000
            },
            "new_basis_count": 17,
            "total_basis_count": 110,
            "H_reduced_size": [
                110,
                110
            ],
            "reduction": 89.2578125,
            "H_reduced_e": -1.288407446743418e-14,
            "used_dense": true,
            "eigenvalue_time": "0:00:00.003930",
            "diff": 1.346634419482504e-14,
            "change_from_prev": 3.926036963649809e-15,
            "circuit_cost": {
                "depth": 198,
                "size": 421,
                "num_2q_ops": 271,
                "count_ops": {
                    "cx": 208,
                    "rz": 60,
                    "u2": 48,
                    "rzz": 24,
                    "unitary": 19,
                    "rzx": 12,
                    "h": 12,
                    "measure": 10,
                    "sxdg": 6,
                    "sx": 6,
                    "u3": 4,
                    "rx": 4,
                    "rxx": 4,
                    "ryy": 4,
                    "barrier": 1
                }
            }
        }
    ],
    "num_jobs": null,
    "QPU_usage": null,
    "job_info": {},
    "sampler_options": {
        "backend_options": {
            "method": "automatic",
            "noise_model": null,
            "seed_simulator": 119836516
        },
        "run_options": {
            "shots": 10000
        }
    }
}