{
    "starttime": "2025-04-09_11-27-39",
    "endtime": "2025-04-09_11-34-01",
    "potential": "DW",
    "cutoff": 32,
    "exact_eigenvalues": [
        0.8916323705551651,
        0.8916323807690868,
        2.7340105966552204,
        2.7340107962998923
    ],
    "ansatz": "circuit.txt",
    "shots": 1024,
    "Optimizer": {
        "name": "differential_evolution",
        "bounds": "[(0, 2 * np.pi)]",
        "maxiter": 5000,
        "tolerance": 0.001,
        "abs_tolerance": 0.01,
        "strategy": "randtobest1bin",
        "popsize": 20,
        "init": "scaled_samples"
    },
    "num_VQE": 40,
    "num_steps": 10,
    "num_grad_checks": 10,
    "phi": 0.0,
    "basis_state": [
        0,
        0,
        0,
        0,
        0,
        0
    ],
    "operator_pool": [
        "RY(0.0, wires=[0])",
        "RZ(0.0, wires=[0])",
        "RY(0.0, wires=[1])",
        "RZ(0.0, wires=[1])",
        "RY(0.0, wires=[2])",
        "RZ(0.0, wires=[2])",
        "RY(0.0, wires=[3])",
        "RZ(0.0, wires=[3])",
        "RY(0.0, wires=[4])",
        "RZ(0.0, wires=[4])",
        "RY(0.0, wires=[5])",
        "RZ(0.0, wires=[5])",
        "CRY(0.0, wires=[0, 1]))",
        "CRY(0.0, wires=[0, 2]))",
        "CRY(0.0, wires=[0, 3]))",
        "CRY(0.0, wires=[0, 4]))",
        "CRY(0.0, wires=[0, 5]))",
        "CRY(0.0, wires=[1, 0]))",
        "CRY(0.0, wires=[1, 2]))",
        "CRY(0.0, wires=[1, 3]))",
        "CRY(0.0, wires=[1, 4]))",
        "CRY(0.0, wires=[1, 5]))",
        "CRY(0.0, wires=[2, 0]))",
        "CRY(0.0, wires=[2, 1]))",
        "CRY(0.0, wires=[2, 3]))",
        "CRY(0.0, wires=[2, 4]))",
        "CRY(0.0, wires=[2, 5]))",
        "CRY(0.0, wires=[3, 0]))",
        "CRY(0.0, wires=[3, 1]))",
        "CRY(0.0, wires=[3, 2]))",
        "CRY(0.0, wires=[3, 4]))",
        "CRY(0.0, wires=[3, 5]))",
        "CRY(0.0, wires=[4, 0]))",
        "CRY(0.0, wires=[4, 1]))",
        "CRY(0.0, wires=[4, 2]))",
        "CRY(0.0, wires=[4, 3]))",
        "CRY(0.0, wires=[4, 5]))",
        "CRY(0.0, wires=[5, 0]))",
        "CRY(0.0, wires=[5, 1]))",
        "CRY(0.0, wires=[5, 2]))",
        "CRY(0.0, wires=[5, 3]))",
        "CRY(0.0, wires=[5, 4]))"
    ],
    "all_energies": [
        [
            0.9636362314757048,
            0.9420099001750546,
            0.9312147152564988,
            0.8954929310922599,
            0.8916323705551273
        ],
        [
            0.980051610486816,
            0.932708580780176,
            0.9373592404776153,
            0.8916323705551273
        ],
        [
            0.995756018199627,
            0.942068111396888,
            0.9067728832083737,
            0.8916323705551273
        ],
        [
            0.9618370339892788,
            0.9211664630997816,
            0.9797485175676249,
            0.9531592619715585,
            0.925817122797221,
            0.897776895776244,
            0.9276163202836468,
            0.9456082951479066,
            0.8916323705551273
        ],
        [
            0.9646057658708208,
            0.985855912529144,
            0.9941780589225714,
            0.9679455977468568,
            1.0250279451800006,
            0.9917740390216704,
            0.8954929310922599,
            0.9085720806947997,
            0.9016374563133766,
            0.8916323705551273
        ],
        [
            0.9761018681028574,
            0.9242800908750756,
            0.924017925310795,
            0.8916323705551273
        ],
        [
            0.9650905330683788,
            0.9722895620576404,
            0.9494688556850392,
            0.9276163202836467,
            0.9384115052022027,
            0.8916323705551273
        ],
        [
            0.9593514706407098,
            0.9229656605862075,
            0.9288875841740467,
            0.8916323705551273
        ],
        [
            0.9760660288413947,
            0.939722333023606,
            0.9042267529601091,
            0.9384115052022026,
            0.8970299630144052,
            0.8916323705551273
        ],
        [
            0.9672346264485567,
            0.9294737289919061,
            0.897776895776244,
            0.8916323705551273
        ],
        [
            0.9696584624363468,
            0.9301624505319115,
            0.9092409558421304,
            0.8934315680415532,
            0.8916323705551273
        ],
        [
            0.9672346264485567,
            0.9193672656133556,
            0.9420099001750546,
            0.8916323705551273
        ],
        [
            0.9798290088535386,
            0.9512248867729971,
            0.9314768808207794,
            0.8916323705551273
        ],
        [
            0.9804557098563564,
            0.937499987401072,
            0.9391584379640413,
            0.910065946218477,
            0.8952307655279792,
            0.8916323705551273
        ],
        [
            0.9726322189078347,
            0.9139696731540776,
            0.9539946889020376,
            0.9989056074384595,
            0.8916323705551273
        ],
        [
            0.9791412795674885,
            0.9471021606715839,
            0.9276163202836468,
            0.9183150008887683,
            0.8916323705551273
        ],
        [
            0.9650905330683788,
            0.9421879719859568,
            0.9039214209973605,
            0.9348131102293507,
            0.8916323705551273
        ],
        [
            0.980051610486816,
            0.9366123077157767,
            0.9380187493183121,
            0.8916323705551273
        ],
        [
            0.9862752635699391,
            0.9410961433303663,
            0.9085720806947998,
            0.9115644844571178,
            0.8916323705551273
        ],
        [
            0.9786962528430376,
            0.9767153810782446,
            0.9319616480183375,
            0.9384115052022026,
            0.9402107026886286,
            0.8916323705551273
        ],
        [
            0.9776835520494537,
            0.9723304894125508,
            0.9478490934334225,
            0.9348131102293507,
            1.0159910303929602,
            0.897776895776244,
            0.8916323705551273
        ],
        [
            0.9678592649499209,
            0.9265640555590595,
            0.9312147152564987,
            0.8954929310922599,
            0.8970299630144052,
            0.8916323705551273
        ],
        [
            0.9762306138806867,
            0.957633816601952,
            0.9420099001750546,
            0.9484165909604518,
            0.9440712632257612,
            0.9090159205374474,
            0.8916323705551273
        ],
        [
            0.9664049633572468,
            0.9815886424089613,
            0.9492066901207585,
            0.9290321281928162,
            0.9096243454193871,
            0.8916323705551273
        ],
        [
            0.9618370339892788,
            0.9352547110284406,
            0.8972921285786859,
            0.8916323705551273
        ],
        [
            0.9641209986732628,
            0.9193672656133556,
            0.9121704756676516,
            0.8954929310922599,
            0.8916323705551273
        ],
        [
            0.9673744977523628,
            0.9474074926343325,
            0.9402107026886286,
            0.8916323705551273
        ],
        [
            0.9636362314757048,
            0.9440712632257613,
            0.9332760783072054,
            0.8970299630144052,
            0.8916323705551273
        ],
        [
            0.9672346264485567,
            0.9366123077157766,
            0.9078251479329611,
            0.8916323705551273
        ],
        [
            0.9618370339892788,
            0.9404728682529092,
            0.9539958576980967,
            0.8954929310922599,
            0.8916323705551273
        ],
        [
            0.9888434489486505,
            0.938106173239454,
            0.9631119003471436,
            0.9316178223720841,
            0.9230052245172108,
            0.8916323705551273
        ],
        [
            0.9734385316875658,
            0.9456082951479066,
            0.9366123077157767,
            0.8916323705551273
        ],
        [
            0.9641209986732628,
            0.9312147152564988,
            0.9951907597161553,
            0.9308313256792422,
            0.9328926887299488,
            0.8995760932626699,
            0.8972921285786859,
            0.8916323705551273
        ],
        [
            0.9673744977523628,
            0.9211664630997816,
            0.915021937878665,
            0.8952307655279792,
            0.9799265893785272,
            0.8993534916293926
        ],
        [
            0.9660600674634949,
            0.9644054139958382,
            0.955792816140965,
            0.8916323705551273
        ],
        [
            0.9690338239349827,
            0.9733791516696735,
            0.9317390463850601,
            0.9963199132591916,
            1.0094537492879532,
            0.9149787714801969,
            0.9733791516696734,
            0.9582026775528883,
            0.9676798297151115,
            0.8916323705551273
        ],
        [
            0.9650905330683788,
            0.9815886424089613,
            0.93990537072588,
            0.9114235429058131,
            0.9434628383438215,
            0.8916323705551273
        ],
        [
            0.9744314163942607,
            0.9276163202836469,
            0.924017925310795,
            0.8916323705551273
        ],
        [
            0.9618370339892788,
            0.9373592404776154,
            0.9492066901207585,
            0.8954929310922599,
            0.8916323705551273
        ],
        [
            0.9641209986732628,
            0.9355600429911893,
            0.9903584257403489,
            0.9308313256792422,
            0.8988291605008312,
            0.8954929310922599,
            0.9836895693906712,
            0.8934315680415532,
            0.920419530337943,
            0.8916323705551273
        ]
    ],
    "min_energies": [
        0.8916323705551273,
        0.8916323705551273,
        0.8916323705551273,
        0.8916323705551273,
        0.8916323705551273,
        0.8916323705551273,
        0.8916323705551273,
        0.8916323705551273,
        0.8916323705551273,
        0.8916323705551273,
        0.8916323705551273,
        0.8916323705551273,
        0.8916323705551273,
        0.8916323705551273,
        0.8916323705551273,
        0.8916323705551273,
        0.8916323705551273,
        0.8916323705551273,
        0.8916323705551273,
        0.8916323705551273,
        0.8916323705551273,
        0.8916323705551273,
        0.8916323705551273,
        0.8916323705551273,
        0.8916323705551273,
        0.8916323705551273,
        0.8916323705551273,
        0.8916323705551273,
        0.8916323705551273,
        0.8916323705551273,
        0.8916323705551273,
        0.8916323705551273,
        0.8916323705551273,
        0.8993534916293926,
        0.8916323705551273,
        0.8916323705551273,
        0.8916323705551273,
        0.8916323705551273,
        0.8916323705551273,
        0.8916323705551273
    ],
    "op_list": [
        [
            {
                "name": "RY",
                "param": 1.1976612576444825,
                "wires": [
                    5
                ]
            },
            {
                "name": "CRY",
                "param": 5.562040468140697,
                "wires": [
                    5,
                    4
                ]
            },
            {
                "name": "RY",
                "param": 6.118492998143514,
                "wires": [
                    3
                ]
            },
            {
                "name": "RY",
                "param": 0.3888680497520367,
                "wires": [
                    4
                ]
            },
            {
                "name": "RY",
                "param": 6.268348384804116,
                "wires": [
                    2
                ]
            }
        ],
        [
            {
                "name": "RY",
                "param": 1.2443904318983519,
                "wires": [
                    5
                ]
            },
            {
                "name": "CRY",
                "param": 5.683843735146622,
                "wires": [
                    5,
                    4
                ]
            },
            {
                "name": "RY",
                "param": 6.135059001760654,
                "wires": [
                    3
                ]
            },
            {
                "name": "RY",
                "param": 0.3088909950273169,
                "wires": [
                    4
                ]
            }
        ],
        [
            {
                "name": "RY",
                "param": 1.2757158869637795,
                "wires": [
                    5
                ]
            },
            {
                "name": "CRY",
                "param": 5.652315937327481,
                "wires": [
                    5,
                    4
                ]
            },
            {
                "name": "RY",
                "param": 0.3061156420247806,
                "wires": [
                    4
                ]
            },
            {
                "name": "RY",
                "param": 6.191999632354732,
                "wires": [
                    3
                ]
            }
        ],
        [
            {
                "name": "RY",
                "param": 1.2274456792448165,
                "wires": [
                    5
                ]
            },
            {
                "name": "CRY",
                "param": 5.862149170533853,
                "wires": [
                    5,
                    4
                ]
            },
            {
                "name": "RY",
                "param": 5.1480159761997655,
                "wires": [
                    3
                ]
            },
            {
                "name": "CRY",
                "param": 0.07553830263927086,
                "wires": [
                    5,
                    3
                ]
            },
            {
                "name": "RY",
                "param": 0.9370790910080475,
                "wires": [
                    3
                ]
            },
            {
                "name": "RY",
                "param": 0.25232310597667684,
                "wires": [
                    4
                ]
            },
            {
                "name": "RY",
                "param": 5.1906932289092085,
                "wires": [
                    2
                ]
            },
            {
                "name": "CRY",
                "param": 0.05104814061051943,
                "wires": [
                    5,
                    2
                ]
            },
            {
                "name": "RY",
                "param": 1.060495293597774,
                "wires": [
                    2
                ]
            }
        ],
        [
            {
                "name": "RY",
                "param": 3.391343930519859,
                "wires": [
                    5
                ]
            },
            {
                "name": "CRY",
                "param": 3.2648901109719852,
                "wires": [
                    5,
                    4
                ]
            },
            {
                "name": "CRY",
                "param": 0.5689864836950163,
                "wires": [
                    5,
                    3
                ]
            },
            {
                "name": "RY",
                "param": 3.154793708916851,
                "wires": [
                    4
                ]
            },
            {
                "name": "RY",
                "param": 5.599266423707479,
                "wires": [
                    3
                ]
            },
            {
                "name": "RY",
                "param": 1.3776021528622766,
                "wires": [
                    2
                ]
            },
            {
                "name": "RY",
                "param": 4.392663410037169,
                "wires": [
                    5
                ]
            },
            {
                "name": "CRY",
                "param": 6.159514231960689,
                "wires": [
                    5,
                    2
                ]
            },
            {
                "name": "RY",
                "param": 4.93765998954449,
                "wires": [
                    2
                ]
            },
            {
                "name": "CRY",
                "param": 0.4782218098937725,
                "wires": [
                    4,
                    3
                ]
            }
        ],
        [
            {
                "name": "RY",
                "param": 1.2951086443664541,
                "wires": [
                    5
                ]
            },
            {
                "name": "CRY",
                "param": 5.618787559264236,
                "wires": [
                    5,
                    4
                ]
            },
            {
                "name": "RY",
                "param": 6.075119072722718,
                "wires": [
                    3
                ]
            },
            {
                "name": "RY",
                "param": 0.3944108072694035,
                "wires": [
                    4
                ]
            }
        ],
        [
            {
                "name": "RY",
                "param": 1.2943108737364142,
                "wires": [
                    5
                ]
            },
            {
                "name": "CRY",
                "param": 5.546200165291184,
                "wires": [
                    5,
                    4
                ]
            },
            {
                "name": "CRY",
                "param": 0.17038964159957803,
                "wires": [
                    5,
                    3
                ]
            },
            {
                "name": "RY",
                "param": 6.081077946413826,
                "wires": [
                    3
                ]
            },
            {
                "name": "RY",
                "param": 0.05482222619521471,
                "wires": [
                    2
                ]
            },
            {
                "name": "RY",
                "param": 0.44783835882032097,
                "wires": [
                    4
                ]
            }
        ],
        [
            {
                "name": "RY",
                "param": 1.3382220351862726,
                "wires": [
                    5
                ]
            },
            {
                "name": "CRY",
                "param": 5.717708410648285,
                "wires": [
                    5,
                    4
                ]
            },
            {
                "name": "RY",
                "param": 0.3039429170210086,
                "wires": [
                    4
                ]
            },
            {
                "name": "RY",
                "param": 6.146688568676852,
                "wires": [
                    3
                ]
            }
        ],
        [
            {
                "name": "RY",
                "param": 2.7622143753710797,
                "wires": [
                    5
                ]
            },
            {
                "name": "CRY",
                "param": 1.851571181217145,
                "wires": [
                    5,
                    4
                ]
            },
            {
                "name": "RY",
                "param": 2.183321049033814,
                "wires": [
                    5
                ]
            },
            {
                "name": "RY",
                "param": 6.108189769834921,
                "wires": [
                    3
                ]
            },
            {
                "name": "RY",
                "param": 4.54586882288441,
                "wires": [
                    4
                ]
            },
            {
                "name": "CRY",
                "param": 0.10093339437712778,
                "wires": [
                    5,
                    3
                ]
            }
        ],
        [
            {
                "name": "RY",
                "param": 1.3157138283667666,
                "wires": [
                    5
                ]
            },
            {
                "name": "CRY",
                "param": 5.791710616168704,
                "wires": [
                    5,
                    4
                ]
            },
            {
                "name": "RY",
                "param": 0.36977756800395856,
                "wires": [
                    4
                ]
            },
            {
                "name": "RY",
                "param": 6.094515188688628,
                "wires": [
                    3
                ]
            }
        ],
        [
            {
                "name": "RY",
                "param": 2.7834714333825983,
                "wires": [
                    5
                ]
            },
            {
                "name": "CRY",
                "param": 1.5772381930012211,
                "wires": [
                    5,
                    4
                ]
            },
            {
                "name": "RY",
                "param": 6.149022180974393,
                "wires": [
                    3
                ]
            },
            {
                "name": "RY",
                "param": 4.943268178184281,
                "wires": [
                    4
                ]
            },
            {
                "name": "RY",
                "param": 2.139730361608952,
                "wires": [
                    5
                ]
            }
        ],
        [
            {
                "name": "RY",
                "param": 1.2468196775842189,
                "wires": [
                    5
                ]
            },
            {
                "name": "CRY",
                "param": 5.682879913983436,
                "wires": [
                    5,
                    4
                ]
            },
            {
                "name": "RY",
                "param": 6.177929629865995,
                "wires": [
                    3
                ]
            },
            {
                "name": "RY",
                "param": 0.38586067945420366,
                "wires": [
                    4
                ]
            }
        ],
        [
            {
                "name": "RY",
                "param": 1.202298408818649,
                "wires": [
                    5
                ]
            },
            {
                "name": "CRY",
                "param": 5.759901234456862,
                "wires": [
                    5,
                    4
                ]
            },
            {
                "name": "RY",
                "param": 6.108644027279906,
                "wires": [
                    3
                ]
            },
            {
                "name": "RY",
                "param": 0.2856137762443809,
                "wires": [
                    4
                ]
            }
        ],
        [
            {
                "name": "RY",
                "param": 2.6603743630618237,
                "wires": [
                    5
                ]
            },
            {
                "name": "CRY",
                "param": 1.6086124209136579,
                "wires": [
                    5,
                    4
                ]
            },
            {
                "name": "RY",
                "param": 4.920258617383917,
                "wires": [
                    4
                ]
            },
            {
                "name": "RY",
                "param": 2.2439302438411097,
                "wires": [
                    5
                ]
            },
            {
                "name": "RY",
                "param": 6.047569069242552,
                "wires": [
                    3
                ]
            },
            {
                "name": "CRY",
                "param": 0.17229351243569724,
                "wires": [
                    5,
                    3
                ]
            }
        ],
        [
            {
                "name": "RY",
                "param": 1.2765528860963584,
                "wires": [
                    5
                ]
            },
            {
                "name": "CRY",
                "param": 5.605992975137813,
                "wires": [
                    5,
                    4
                ]
            },
            {
                "name": "RY",
                "param": 0.4018197462659012,
                "wires": [
                    4
                ]
            },
            {
                "name": "CRY",
                "param": 0.1913384258922881,
                "wires": [
                    5,
                    3
                ]
            },
            {
                "name": "RY",
                "param": 6.087512748862089,
                "wires": [
                    3
                ]
            }
        ],
        [
            {
                "name": "RY",
                "param": 2.483594170553137,
                "wires": [
                    5
                ]
            },
            {
                "name": "CRY",
                "param": 1.1699767378020967,
                "wires": [
                    5,
                    4
                ]
            },
            {
                "name": "RY",
                "param": 6.101247994939245,
                "wires": [
                    3
                ]
            },
            {
                "name": "RY",
                "param": 5.385005685982858,
                "wires": [
                    4
                ]
            },
            {
                "name": "RY",
                "param": 2.5310821333393787,
                "wires": [
                    5
                ]
            }
        ],
        [
            {
                "name": "RY",
                "param": 2.8991057265791604,
                "wires": [
                    5
                ]
            },
            {
                "name": "CRY",
                "param": 2.7683057797841464,
                "wires": [
                    5,
                    4
                ]
            },
            {
                "name": "RY",
                "param": 1.9051742754944376,
                "wires": [
                    5
                ]
            },
            {
                "name": "RY",
                "param": 6.166836555086344,
                "wires": [
                    3
                ]
            },
            {
                "name": "RY",
                "param": 3.6807938671454634,
                "wires": [
                    4
                ]
            }
        ],
        [
            {
                "name": "RY",
                "param": 1.2973964653565737,
                "wires": [
                    5
                ]
            },
            {
                "name": "CRY",
                "param": 5.483250793530246,
                "wires": [
                    5,
                    4
                ]
            },
            {
                "name": "RY",
                "param": 6.102943685152472,
                "wires": [
                    3
                ]
            },
            {
                "name": "RY",
                "param": 0.3867900760362093,
                "wires": [
                    4
                ]
            }
        ],
        [
            {
                "name": "RY",
                "param": 1.8912881533622679,
                "wires": [
                    5
                ]
            },
            {
                "name": "CRY",
                "param": 0.6306445226282893,
                "wires": [
                    5,
                    4
                ]
            },
            {
                "name": "RY",
                "param": 5.956769830577577,
                "wires": [
                    4
                ]
            },
            {
                "name": "RY",
                "param": 6.116891481151068,
                "wires": [
                    3
                ]
            },
            {
                "name": "RY",
                "param": 3.1364933730651017,
                "wires": [
                    5
                ]
            }
        ],
        [
            {
                "name": "RY",
                "param": 1.2905295503037875,
                "wires": [
                    5
                ]
            },
            {
                "name": "CRY",
                "param": 5.611086848788756,
                "wires": [
                    5,
                    4
                ]
            },
            {
                "name": "CRY",
                "param": 0.012130980517624401,
                "wires": [
                    5,
                    3
                ]
            },
            {
                "name": "RY",
                "param": 6.116882272344448,
                "wires": [
                    3
                ]
            },
            {
                "name": "RY",
                "param": 0.037224668645007064,
                "wires": [
                    2
                ]
            },
            {
                "name": "RY",
                "param": 0.3937707271595885,
                "wires": [
                    4
                ]
            }
        ],
        [
            {
                "name": "RY",
                "param": 3.611159681865482,
                "wires": [
                    5
                ]
            },
            {
                "name": "CRY",
                "param": 1.2066897185582317,
                "wires": [
                    5,
                    4
                ]
            },
            {
                "name": "CRY",
                "param": 6.049441167296501,
                "wires": [
                    5,
                    3
                ]
            },
            {
                "name": "RY",
                "param": 0.09904682745706062,
                "wires": [
                    3
                ]
            },
            {
                "name": "RY",
                "param": 5.2777024495451155,
                "wires": [
                    4
                ]
            },
            {
                "name": "RY",
                "param": 2.35016709863263,
                "wires": [
                    5
                ]
            },
            {
                "name": "RY",
                "param": 0.012479443650815547,
                "wires": [
                    2
                ]
            }
        ],
        [
            {
                "name": "RY",
                "param": 1.3058194443409679,
                "wires": [
                    5
                ]
            },
            {
                "name": "CRY",
                "param": 5.70098387875634,
                "wires": [
                    5,
                    4
                ]
            },
            {
                "name": "RY",
                "param": 6.10036482230066,
                "wires": [
                    3
                ]
            },
            {
                "name": "RY",
                "param": 0.3332726218582027,
                "wires": [
                    4
                ]
            },
            {
                "name": "RY",
                "param": 0.008453332606269015,
                "wires": [
                    2
                ]
            },
            {
                "name": "CRY",
                "param": 0.15469298898433648,
                "wires": [
                    5,
                    3
                ]
            }
        ],
        [
            {
                "name": "RY",
                "param": 3.4867315829836922,
                "wires": [
                    5
                ]
            },
            {
                "name": "CRY",
                "param": 4.435838535119895,
                "wires": [
                    5,
                    4
                ]
            },
            {
                "name": "CRY",
                "param": 6.059861958295002,
                "wires": [
                    5,
                    3
                ]
            },
            {
                "name": "RY",
                "param": 2.036979850495115,
                "wires": [
                    4
                ]
            },
            {
                "name": "RY",
                "param": 0.08671876644521381,
                "wires": [
                    3
                ]
            },
            {
                "name": "RY",
                "param": 6.2794760507383725,
                "wires": [
                    2
                ]
            },
            {
                "name": "RY",
                "param": 1.7046940717822057,
                "wires": [
                    5
                ]
            }
        ],
        [
            {
                "name": "RY",
                "param": 1.3181986953782094,
                "wires": [
                    5
                ]
            },
            {
                "name": "CRY",
                "param": 5.711191795808546,
                "wires": [
                    5,
                    4
                ]
            },
            {
                "name": "CRY",
                "param": 0.3491170059320159,
                "wires": [
                    5,
                    3
                ]
            },
            {
                "name": "RY",
                "param": 5.97499333199459,
                "wires": [
                    3
                ]
            },
            {
                "name": "RY",
                "param": 0.30982661548375656,
                "wires": [
                    4
                ]
            },
            {
                "name": "RY",
                "param": 0.011058046652578923,
                "wires": [
                    2
                ]
            }
        ],
        [
            {
                "name": "RY",
                "param": 1.2496733643598052,
                "wires": [
                    5
                ]
            },
            {
                "name": "CRY",
                "param": 5.639637474375424,
                "wires": [
                    5,
                    4
                ]
            },
            {
                "name": "RY",
                "param": 0.2825412461082424,
                "wires": [
                    4
                ]
            },
            {
                "name": "RY",
                "param": 6.14959675514352,
                "wires": [
                    3
                ]
            }
        ],
        [
            {
                "name": "RY",
                "param": 1.2244522276976797,
                "wires": [
                    5
                ]
            },
            {
                "name": "CRY",
                "param": 5.692568863327079,
                "wires": [
                    5,
                    4
                ]
            },
            {
                "name": "RY",
                "param": 6.106326567508473,
                "wires": [
                    3
                ]
            },
            {
                "name": "RY",
                "param": 0.35473752443048134,
                "wires": [
                    4
                ]
            },
            {
                "name": "RY",
                "param": 6.266967014569451,
                "wires": [
                    2
                ]
            }
        ],
        [
            {
                "name": "RY",
                "param": 1.2511305026488833,
                "wires": [
                    5
                ]
            },
            {
                "name": "CRY",
                "param": 5.8089897073040415,
                "wires": [
                    5,
                    4
                ]
            },
            {
                "name": "RY",
                "param": 6.135081624788595,
                "wires": [
                    3
                ]
            },
            {
                "name": "RY",
                "param": 0.2531904538698333,
                "wires": [
                    4
                ]
            }
        ],
        [
            {
                "name": "RY",
                "param": 1.2742261427625612,
                "wires": [
                    5
                ]
            },
            {
                "name": "CRY",
                "param": 5.581133291989209,
                "wires": [
                    5,
                    4
                ]
            },
            {
                "name": "RY",
                "param": 6.086638252321041,
                "wires": [
                    3
                ]
            },
            {
                "name": "RY",
                "param": 0.43094683947874657,
                "wires": [
                    4
                ]
            },
            {
                "name": "CRY",
                "param": 0.03337791094213394,
                "wires": [
                    5,
                    3
                ]
            }
        ],
        [
            {
                "name": "RY",
                "param": 1.2735296234416986,
                "wires": [
                    5
                ]
            },
            {
                "name": "CRY",
                "param": 5.711942336110419,
                "wires": [
                    5,
                    4
                ]
            },
            {
                "name": "RY",
                "param": 6.1562001977989524,
                "wires": [
                    3
                ]
            },
            {
                "name": "RY",
                "param": 0.39702258558142267,
                "wires": [
                    4
                ]
            }
        ],
        [
            {
                "name": "RY",
                "param": 1.292301551646305,
                "wires": [
                    5
                ]
            },
            {
                "name": "CRY",
                "param": 5.437870836118664,
                "wires": [
                    5,
                    4
                ]
            },
            {
                "name": "RY",
                "param": 6.127593943212018,
                "wires": [
                    3
                ]
            },
            {
                "name": "RY",
                "param": 0.40169737332653144,
                "wires": [
                    4
                ]
            },
            {
                "name": "RY",
                "param": 6.275166960369802,
                "wires": [
                    2
                ]
            }
        ],
        [
            {
                "name": "RY",
                "param": 1.2917698350217681,
                "wires": [
                    5
                ]
            },
            {
                "name": "CRY",
                "param": 5.586326831886392,
                "wires": [
                    5,
                    4
                ]
            },
            {
                "name": "RY",
                "param": 1.412265383109046,
                "wires": [
                    3
                ]
            },
            {
                "name": "CRY",
                "param": 0.14694119876903455,
                "wires": [
                    5,
                    3
                ]
            },
            {
                "name": "RY",
                "param": 4.6975773314437985,
                "wires": [
                    3
                ]
            },
            {
                "name": "RY",
                "param": 0.3847369564023717,
                "wires": [
                    4
                ]
            }
        ],
        [
            {
                "name": "RY",
                "param": 1.2912154837151972,
                "wires": [
                    5
                ]
            },
            {
                "name": "CRY",
                "param": 5.80906228338308,
                "wires": [
                    5,
                    4
                ]
            },
            {
                "name": "RY",
                "param": 6.066736390276473,
                "wires": [
                    3
                ]
            },
            {
                "name": "RY",
                "param": 0.24441777931950126,
                "wires": [
                    4
                ]
            }
        ],
        [
            {
                "name": "RY",
                "param": 3.7096379896953264,
                "wires": [
                    5
                ]
            },
            {
                "name": "CRY",
                "param": 0.9597080344642368,
                "wires": [
                    5,
                    4
                ]
            },
            {
                "name": "RY",
                "param": 4.751337972812124,
                "wires": [
                    3
                ]
            },
            {
                "name": "CRY",
                "param": 5.963853954026112,
                "wires": [
                    5,
                    3
                ]
            },
            {
                "name": "RY",
                "param": 1.7299181028134027,
                "wires": [
                    3
                ]
            },
            {
                "name": "RY",
                "param": 5.407160154117262,
                "wires": [
                    4
                ]
            },
            {
                "name": "RY",
                "param": 2.4301455660874023,
                "wires": [
                    5
                ]
            },
            {
                "name": "RY",
                "param": 6.22979934934888,
                "wires": [
                    2
                ]
            }
        ],
        [
            {
                "name": "RY",
                "param": 2.867176545101718,
                "wires": [
                    5
                ]
            },
            {
                "name": "CRY",
                "param": 2.6203762039882506,
                "wires": [
                    5,
                    4
                ]
            },
            {
                "name": "RY",
                "param": 5.595929174516499,
                "wires": [
                    3
                ]
            },
            {
                "name": "RY",
                "param": 3.821488563589091,
                "wires": [
                    4
                ]
            },
            {
                "name": "CRY",
                "param": 0.4626227644972327,
                "wires": [
                    5,
                    3
                ]
            },
            {
                "name": "RY",
                "param": 2.073391168532442,
                "wires": [
                    5
                ]
            }
        ],
        [
            {
                "name": "RY",
                "param": 1.3114445179069167,
                "wires": [
                    5
                ]
            },
            {
                "name": "CRY",
                "param": 5.564060043548552,
                "wires": [
                    5,
                    4
                ]
            },
            {
                "name": "RY",
                "param": 6.1574609353034715,
                "wires": [
                    3
                ]
            },
            {
                "name": "RY",
                "param": 0.3758701391762358,
                "wires": [
                    4
                ]
            }
        ],
        [
            {
                "name": "RY",
                "param": 3.813425651544766,
                "wires": [
                    5
                ]
            },
            {
                "name": "CRY",
                "param": 0.9083323128840557,
                "wires": [
                    5,
                    4
                ]
            },
            {
                "name": "CRY",
                "param": 6.043535641850888,
                "wires": [
                    5,
                    3
                ]
            },
            {
                "name": "RY",
                "param": 0.10518032180462278,
                "wires": [
                    3
                ]
            },
            {
                "name": "RY",
                "param": 5.641112924735957,
                "wires": [
                    4
                ]
            },
            {
                "name": "RY",
                "param": 4.79161366671404,
                "wires": [
                    2
                ]
            },
            {
                "name": "CRY",
                "param": 0.18561237329199587,
                "wires": [
                    5,
                    2
                ]
            },
            {
                "name": "RY",
                "param": 1.339446385711763,
                "wires": [
                    2
                ]
            },
            {
                "name": "RY",
                "param": 2.5305367636303115,
                "wires": [
                    5
                ]
            },
            {
                "name": "CRY",
                "param": 0.011827035144344578,
                "wires": [
                    5,
                    1
                ]
            }
        ],
        [
            {
                "name": "RY",
                "param": 5.031326574130642,
                "wires": [
                    5
                ]
            },
            {
                "name": "CRY",
                "param": 5.565305126770713,
                "wires": [
                    5,
                    4
                ]
            },
            {
                "name": "CRY",
                "param": 6.264564792265149,
                "wires": [
                    5,
                    3
                ]
            },
            {
                "name": "RY",
                "param": 6.172592308585596,
                "wires": [
                    3
                ]
            },
            {
                "name": "RY",
                "param": 6.272424627907622,
                "wires": [
                    2
                ]
            },
            {
                "name": "RY",
                "param": 0.43831078304461,
                "wires": [
                    4
                ]
            }
        ],
        [
            {
                "name": "RY",
                "param": 1.17449394581528,
                "wires": [
                    5
                ]
            },
            {
                "name": "CRY",
                "param": 5.668995506308532,
                "wires": [
                    5,
                    4
                ]
            },
            {
                "name": "RY",
                "param": 6.14417468247621,
                "wires": [
                    3
                ]
            },
            {
                "name": "RY",
                "param": 0.3201048149899428,
                "wires": [
                    4
                ]
            }
        ],
        [
            {
                "name": "RY",
                "param": 1.254466564070131,
                "wires": [
                    5
                ]
            },
            {
                "name": "CRY",
                "param": 5.667281583777923,
                "wires": [
                    5,
                    4
                ]
            },
            {
                "name": "RY",
                "param": 6.1040468762217595,
                "wires": [
                    3
                ]
            },
            {
                "name": "RY",
                "param": 0.3690220443589234,
                "wires": [
                    4
                ]
            },
            {
                "name": "RY",
                "param": 0.025782263686058293,
                "wires": [
                    2
                ]
            }
        ],
        [
            {
                "name": "RY",
                "param": 2.698542865845682,
                "wires": [
                    5
                ]
            },
            {
                "name": "CRY",
                "param": 1.458146094866931,
                "wires": [
                    5,
                    4
                ]
            },
            {
                "name": "RY",
                "param": 1.7402428810408723,
                "wires": [
                    3
                ]
            },
            {
                "name": "CRY",
                "param": 5.999396384507253,
                "wires": [
                    5,
                    3
                ]
            },
            {
                "name": "RY",
                "param": 5.003916066733526,
                "wires": [
                    4
                ]
            },
            {
                "name": "RY",
                "param": 4.623547351233512,
                "wires": [
                    3
                ]
            },
            {
                "name": "RY",
                "param": 5.876821975444486,
                "wires": [
                    2
                ]
            },
            {
                "name": "RY",
                "param": 3.995206573939672,
                "wires": [
                    5
                ]
            },
            {
                "name": "CRY",
                "param": 6.119661746794998,
                "wires": [
                    5,
                    2
                ]
            },
            {
                "name": "RY",
                "param": 0.4656893637040933,
                "wires": [
                    2
                ]
            }
        ]
    ],
    "num_iters": [
        5,
        4,
        4,
        9,
        10,
        4,
        6,
        4,
        6,
        4,
        5,
        4,
        4,
        6,
        5,
        5,
        5,
        4,
        5,
        6,
        7,
        6,
        7,
        6,
        4,
        5,
        4,
        5,
        4,
        5,
        6,
        4,
        8,
        7,
        4,
        10,
        6,
        4,
        5,
        10
    ],
    "success": [
        true,
        true,
        true,
        true,
        true,
        true,
        true,
        true,
        true,
        true,
        true,
        true,
        true,
        true,
        true,
        true,
        true,
        true,
        true,
        true,
        true,
        true,
        true,
        true,
        true,
        true,
        true,
        true,
        true,
        true,
        true,
        true,
        true,
        true,
        true,
        true,
        true,
        true,
        true,
        true
    ],
    "run_times": [
        "0:00:40.079889",
        "0:00:27.422872",
        "0:00:24.196910",
        "0:03:05.347063",
        "0:03:18.038177",
        "0:00:35.247972",
        "0:01:02.901179",
        "0:00:58.624685",
        "0:03:48.726831",
        "0:00:36.880685",
        "0:00:50.983521",
        "0:00:32.786478",
        "0:00:29.470210",
        "0:00:53.533956",
        "0:01:21.689648",
        "0:00:45.305497",
        "0:05:57.647423",
        "0:00:28.576535",
        "0:00:41.241128",
        "0:01:02.363068",
        "0:01:28.098512",
        "0:00:50.625188",
        "0:01:32.066324",
        "0:01:15.886609",
        "0:00:32.507522",
        "0:00:45.499678",
        "0:00:33.681556",
        "0:00:39.906292",
        "0:00:36.149093",
        "0:00:42.886684",
        "0:01:20.149824",
        "0:00:29.545125",
        "0:01:42.175494",
        "0:01:32.587994",
        "0:00:32.109100",
        "0:06:22.039016",
        "0:01:12.183354",
        "0:00:32.629890",
        "0:00:41.946839",
        "0:03:46.668336"
    ],
    "seeds": [
        31623573,
        47422986,
        63222399,
        79021812,
        94821225,
        110620638,
        2963262,
        18762675,
        34562088,
        50361501,
        66160914,
        81960327,
        97759740,
        113559153,
        5901777,
        21701190,
        37500603,
        53300016,
        69099429,
        84898842,
        100698255,
        116497668,
        8840292,
        24639705,
        40439118,
        56238531,
        72037944,
        87837357,
        103636770,
        119436183,
        11778807,
        27578220,
        43377633,
        59177046,
        74976459,
        90775872,
        106575285,
        122374698,
        14717322,
        30516735
    ],
    "parallel_run_time": "0:06:22.275762",
    "total_VQE_time": "0:55:10.406157",
    "total_device_time": "0:01:21.508729"
}