{
    "seed": 78201396,
    "starttime": "2026-01-20_09-33-45",
    "endtime": "2026-01-20_09-35-43",
    "time_taken": "0:01:58.374804",
    "H_info": {
        "potential": "linear",
        "boundary_condition": "dirichlet",
        "cutoff": 4,
        "N": 6,
        "a": 1.0,
        "c": null,
        "num_qubits": 18,
        "num_paulis": 105,
        "keep_ratio": 0.999,
        "trunc_info": {
            "m": 64,
            "n": 105,
            "keep_frac_terms": 0.6095238095238096,
            "keep_ratio": 0.999,
            "truncated": 0.09418075211979726,
            "total_weight": 125.625
        },
        "dense_H_size": [
            262144,
            262144
        ],
        "eigenvalues": [
            -0.000315510067988475,
            0.8643770070861958,
            0.8643770070862011,
            0.9732515345014151,
            0.97325153450142,
            1.0241431596931485,
            1.0241431596931516,
            1.044907072996391
        ],
        "basis": [
            0,
            0,
            0,
            0,
            0,
            1,
            0,
            0,
            0,
            0,
            0,
            1,
            0,
            0,
            0,
            0,
            0,
            1
        ]
    },
    "backend_info": {
        "backend_name": "Aer",
        "use_noise_model": 0,
        "noise_model_options": {
            "gate_error": true,
            "readout_error": true,
            "thermal_relaxation": true
        },
        "resilience_level": 2,
        "optimization_level": 3,
        "shots": 10000,
        "tags": [
            "NQCC-Q4",
            "SBQKD",
            "shots:10000",
            "dirichlet",
            "linear",
            "N=6",
            "cutoff=4"
        ]
    },
    "Ansatz_info": {
        "include_basis": true,
        "include_rys": false,
        "include_xxyys": false
    },
    "run_info": {
        "dt": 3.0,
        "max_k": 40,
        "tol": 1e-08,
        "conserve_fermion": true,
        "fermion_qubits": [
            2,
            5,
            8,
            11,
            14,
            17
        ],
        "num_fermions": 3,
        "trotter_patience": 2,
        "energy_patience": 3,
        "max_n_steps": 3
    },
    "final_k": 38,
    "converged": false,
    "all_energies": [
        4.548691564414126,
        2.338601564968404,
        2.3386002152958105,
        2.3377218460437903,
        2.3377211994289553,
        2.2114792000624948,
        2.111649433166443,
        1.9687116977416523,
        1.9687116956604005,
        1.9288369637060305,
        1.8846267809878037,
        1.8845786070505661,
        1.8844653845783226,
        1.8826132005353338,
        1.8688124144402731,
        1.8687688579078503,
        0.0004861969553700674,
        0.00048109424328956514,
        0.00041574813931701324,
        0.0004157481388868097,
        0.0003960738112787866,
        0.00019657793150924802,
        0.00017261730302427697,
        -1.8364986328211006e-05,
        -1.8369163839683313e-05,
        -3.654533780810566e-05,
        -8.159613473273488e-05,
        -8.297720194293068e-05,
        -8.454069044817711e-05,
        -8.56039566550918e-05,
        -9.061944502565356e-05,
        -9.090092553957398e-05,
        -9.254234796012244e-05,
        -9.25423479588011e-05,
        -9.256699334212802e-05,
        -9.258797193002327e-05,
        -9.258806017474453e-05,
        -9.258806016980463e-05
    ],
    "all_run_data": [
        {
            "D": 1,
            "t": 3.0,
            "num_trotter_steps": 1,
            "circuit_time": "0:00:00.105514",
            "shot_processing": {
                "raw_unique_basis_states": 805,
                "fermion_basis_rejected": 0,
                "kept_unique_basis_states": 805,
                "fermion_shots_rejected": 0,
                "kept_shots": 10000
            },
            "new_basis_count": 805,
            "total_basis_count": 805,
            "H_reduced_size": [
                805,
                805
            ],
            "reduction": 99.69291687011719,
            "H_reduced_e": 4.548691564414126,
            "used_dense": true,
            "eigenvalue_time": "0:00:00.507101",
            "diff": 4.549007074482114,
            "change_from_prev": null,
            "circuit_cost": {
                "depth": 78,
                "size": 213,
                "num_2q_ops": 111,
                "count_ops": {
                    "cx": 84,
                    "u2": 27,
                    "rz": 24,
                    "measure": 18,
                    "sxdg": 10,
                    "rxx": 9,
                    "h": 9,
                    "sx": 7,
                    "rzz": 6,
                    "u3": 6,
                    "ryy": 5,
                    "rzx": 4,
                    "unitary": 3,
                    "u1": 1,
                    "barrier": 1
                }
            }
        },
        {
            "D": 2,
            "t": 6.0,
            "num_trotter_steps": 1,
            "circuit_time": "0:00:00.090018",
            "shot_processing": {
                "raw_unique_basis_states": 959,
                "fermion_basis_rejected": 0,
                "kept_unique_basis_states": 959,
                "fermion_shots_rejected": 0,
                "kept_shots": 10000
            },
            "new_basis_count": 957,
            "total_basis_count": 1762,
            "H_reduced_size": [
                1762,
                1762
            ],
            "reduction": 99.32785034179688,
            "H_reduced_e": 2.338601564968404,
            "used_dense": true,
            "eigenvalue_time": "0:00:04.286870",
            "diff": 2.3389170750363926,
            "change_from_prev": 2.2100899994457217,
            "circuit_cost": {
                "depth": 78,
                "size": 213,
                "num_2q_ops": 111,
                "count_ops": {
                    "cx": 84,
                    "u2": 27,
                    "rz": 24,
                    "measure": 18,
                    "sxdg": 10,
                    "rxx": 9,
                    "h": 9,
                    "sx": 7,
                    "rzz": 6,
                    "u3": 6,
                    "ryy": 5,
                    "rzx": 4,
                    "unitary": 3,
                    "u1": 1,
                    "barrier": 1
                }
            }
        },
        {
            "D": 3,
            "t": 9.0,
            "num_trotter_steps": 1,
            "circuit_time": "0:00:00.091665",
            "shot_processing": {
                "raw_unique_basis_states": 1246,
                "fermion_basis_rejected": 0,
                "kept_unique_basis_states": 1246,
                "fermion_shots_rejected": 0,
                "kept_shots": 10000
            },
            "new_basis_count": 694,
            "total_basis_count": 2456,
            "H_reduced_size": [
                2456,
                2456
            ],
            "reduction": 99.0631103515625,
            "H_reduced_e": 2.3386002152958105,
            "used_dense": false,
            "eigenvalue_time": "0:00:00.019611",
            "diff": 2.338915725363799,
            "change_from_prev": 1.3496725936867904e-06,
            "circuit_cost": {
                "depth": 78,
                "size": 213,
                "num_2q_ops": 111,
                "count_ops": {
                    "cx": 84,
                    "u2": 27,
                    "rz": 24,
                    "measure": 18,
                    "sxdg": 10,
                    "rxx": 9,
                    "h": 9,
                    "sx": 7,
                    "rzz": 6,
                    "u3": 6,
                    "ryy": 5,
                    "rzx": 4,
                    "unitary": 3,
                    "u1": 1,
                    "barrier": 1
                }
            }
        },
        {
            "D": 4,
            "t": 12.0,
            "num_trotter_steps": 1,
            "circuit_time": "0:00:00.089508",
            "shot_processing": {
                "raw_unique_basis_states": 1579,
                "fermion_basis_rejected": 0,
                "kept_unique_basis_states": 1579,
                "fermion_shots_rejected": 0,
                "kept_shots": 10000
            },
            "new_basis_count": 1255,
            "total_basis_count": 3711,
            "H_reduced_size": [
                3711,
                3711
            ],
            "reduction": 98.58436584472656,
            "H_reduced_e": 2.3377218460437903,
            "used_dense": false,
            "eigenvalue_time": "0:00:00.026562",
            "diff": 2.3380373561117787,
            "change_from_prev": 0.000878369252020228,
            "circuit_cost": {
                "depth": 78,
                "size": 213,
                "num_2q_ops": 111,
                "count_ops": {
                    "cx": 84,
                    "u2": 27,
                    "rz": 24,
                    "measure": 18,
                    "sxdg": 10,
                    "rxx": 9,
                    "h": 9,
                    "sx": 7,
                    "rzz": 6,
                    "u3": 6,
                    "ryy": 5,
                    "rzx": 4,
                    "unitary": 3,
                    "u1": 1,
                    "barrier": 1
                }
            }
        },
        {
            "D": 5,
            "t": 15.0,
            "num_trotter_steps": 1,
            "circuit_time": "0:00:00.090876",
            "shot_processing": {
                "raw_unique_basis_states": 1062,
                "fermion_basis_rejected": 0,
                "kept_unique_basis_states": 1062,
                "fermion_shots_rejected": 0,
                "kept_shots": 10000
            },
            "new_basis_count": 554,
            "total_basis_count": 4265,
            "H_reduced_size": [
                4265,
                4265
            ],
            "reduction": 98.37303161621094,
            "H_reduced_e": 2.3377211994289553,
            "used_dense": false,
            "eigenvalue_time": "0:00:00.030125",
            "diff": 2.3380367094969436,
            "change_from_prev": 6.466148350092737e-07,
            "circuit_cost": {
                "depth": 78,
                "size": 213,
                "num_2q_ops": 111,
                "count_ops": {
                    "cx": 84,
                    "u2": 27,
                    "rz": 24,
                    "measure": 18,
                    "sxdg": 10,
                    "rxx": 9,
                    "h": 9,
                    "sx": 7,
                    "rzz": 6,
                    "u3": 6,
                    "ryy": 5,
                    "rzx": 4,
                    "unitary": 3,
                    "u1": 1,
                    "barrier": 1
                }
            }
        },
        {
            "D": 6,
            "t": 18.0,
            "num_trotter_steps": 1,
            "circuit_time": "0:00:00.088700",
            "shot_processing": {
                "raw_unique_basis_states": 3240,
                "fermion_basis_rejected": 0,
                "kept_unique_basis_states": 3240,
                "fermion_shots_rejected": 0,
                "kept_shots": 10000
            },
            "new_basis_count": 2026,
            "total_basis_count": 6291,
            "H_reduced_size": [
                6291,
                6291
            ],
            "reduction": 97.60017395019531,
            "H_reduced_e": 2.2114792000624948,
            "used_dense": false,
            "eigenvalue_time": "0:00:00.059914",
            "diff": 2.211794710130483,
            "change_from_prev": 0.12624199936646052,
            "circuit_cost": {
                "depth": 78,
                "size": 213,
                "num_2q_ops": 111,
                "count_ops": {
                    "cx": 84,
                    "u2": 27,
                    "rz": 24,
                    "measure": 18,
                    "sxdg": 10,
                    "rxx": 9,
                    "h": 9,
                    "sx": 7,
                    "rzz": 6,
                    "u3": 6,
                    "ryy": 5,
                    "rzx": 4,
                    "unitary": 3,
                    "u1": 1,
                    "barrier": 1
                }
            }
        },
        {
            "D": 7,
            "t": 21.0,
            "num_trotter_steps": 1,
            "circuit_time": "0:00:00.090354",
            "shot_processing": {
                "raw_unique_basis_states": 1763,
                "fermion_basis_rejected": 0,
                "kept_unique_basis_states": 1763,
                "fermion_shots_rejected": 0,
                "kept_shots": 10000
            },
            "new_basis_count": 876,
            "total_basis_count": 7167,
            "H_reduced_size": [
                7167,
                7167
            ],
            "reduction": 97.26600646972656,
            "H_reduced_e": 2.111649433166443,
            "used_dense": false,
            "eigenvalue_time": "0:00:00.071873",
            "diff": 2.1119649432344314,
            "change_from_prev": 0.09982976689605172,
            "circuit_cost": {
                "depth": 78,
                "size": 213,
                "num_2q_ops": 111,
                "count_ops": {
                    "cx": 84,
                    "u2": 27,
                    "rz": 24,
                    "measure": 18,
                    "sxdg": 10,
                    "rxx": 9,
                    "h": 9,
                    "sx": 7,
                    "rzz": 6,
                    "u3": 6,
                    "ryy": 5,
                    "rzx": 4,
                    "unitary": 3,
                    "u1": 1,
                    "barrier": 1
                }
            }
        },
        {
            "D": 8,
            "t": 24.0,
            "num_trotter_steps": 1,
            "circuit_time": "0:00:00.096816",
            "shot_processing": {
                "raw_unique_basis_states": 3475,
                "fermion_basis_rejected": 0,
                "kept_unique_basis_states": 3475,
                "fermion_shots_rejected": 0,
                "kept_shots": 10000
            },
            "new_basis_count": 1593,
            "total_basis_count": 8760,
            "H_reduced_size": [
                8760,
                8760
            ],
            "reduction": 96.6583251953125,
            "H_reduced_e": 1.9687116977416523,
            "used_dense": false,
            "eigenvalue_time": "0:00:00.092722",
            "diff": 1.969027207809641,
            "change_from_prev": 0.1429377354247907,
            "circuit_cost": {
                "depth": 78,
                "size": 213,
                "num_2q_ops": 111,
                "count_ops": {
                    "cx": 84,
                    "u2": 27,
                    "rz": 24,
                    "measure": 18,
                    "sxdg": 10,
                    "rxx": 9,
                    "h": 9,
                    "sx": 7,
                    "rzz": 6,
                    "u3": 6,
                    "ryy": 5,
                    "rzx": 4,
                    "unitary": 3,
                    "u1": 1,
                    "barrier": 1
                }
            }
        },
        {
            "D": 9,
            "t": 27.0,
            "num_trotter_steps": 1,
            "circuit_time": "0:00:00.093484",
            "shot_processing": {
                "raw_unique_basis_states": 162,
                "fermion_basis_rejected": 0,
                "kept_unique_basis_states": 162,
                "fermion_shots_rejected": 0,
                "kept_shots": 10000
            },
            "new_basis_count": 16,
            "total_basis_count": 8776,
            "H_reduced_size": [
                8776,
                8776
            ],
            "reduction": 96.6522216796875,
            "H_reduced_e": 1.9687116956604005,
            "used_dense": false,
            "eigenvalue_time": "0:00:00.084171",
            "diff": 1.969027205728389,
            "change_from_prev": 2.081251837537934e-09,
            "circuit_cost": {
                "depth": 78,
                "size": 213,
                "num_2q_ops": 111,
                "count_ops": {
                    "cx": 84,
                    "u2": 27,
                    "rz": 24,
                    "measure": 18,
                    "sxdg": 10,
                    "rxx": 9,
                    "h": 9,
                    "sx": 7,
                    "rzz": 6,
                    "u3": 6,
                    "ryy": 5,
                    "rzx": 4,
                    "unitary": 3,
                    "u1": 1,
                    "barrier": 1
                }
            }
        },
        {
            "D": 10,
            "t": 30.0,
            "num_trotter_steps": 1,
            "circuit_time": "0:00:00.085395",
            "shot_processing": {
                "raw_unique_basis_states": 4345,
                "fermion_basis_rejected": 0,
                "kept_unique_basis_states": 4345,
                "fermion_shots_rejected": 0,
                "kept_shots": 10000
            },
            "new_basis_count": 1117,
            "total_basis_count": 9893,
            "H_reduced_size": [
                9893,
                9893
            ],
            "reduction": 96.22611999511719,
            "H_reduced_e": 1.9288369637060305,
            "used_dense": false,
            "eigenvalue_time": "0:00:00.102522",
            "diff": 1.929152473774019,
            "change_from_prev": 0.03987473195436997,
            "circuit_cost": {
                "depth": 78,
                "size": 213,
                "num_2q_ops": 111,
                "count_ops": {
                    "cx": 84,
                    "u2": 27,
                    "rz": 24,
                    "measure": 18,
                    "sxdg": 10,
                    "rxx": 9,
                    "h": 9,
                    "sx": 7,
                    "rzz": 6,
                    "u3": 6,
                    "ryy": 5,
                    "rzx": 4,
                    "unitary": 3,
                    "u1": 1,
                    "barrier": 1
                }
            }
        },
        {
            "D": 11,
            "t": 33.0,
            "num_trotter_steps": 1,
            "circuit_time": "0:00:00.092320",
            "shot_processing": {
                "raw_unique_basis_states": 2214,
                "fermion_basis_rejected": 0,
                "kept_unique_basis_states": 2214,
                "fermion_shots_rejected": 0,
                "kept_shots": 10000
            },
            "new_basis_count": 267,
            "total_basis_count": 10160,
            "H_reduced_size": [
                10160,
                10160
            ],
            "reduction": 96.124267578125,
            "H_reduced_e": 1.8846267809878037,
            "used_dense": false,
            "eigenvalue_time": "0:00:00.109870",
            "diff": 1.8849422910557923,
            "change_from_prev": 0.044210182718226854,
            "circuit_cost": {
                "depth": 78,
                "size": 213,
                "num_2q_ops": 111,
                "count_ops": {
                    "cx": 84,
                    "u2": 27,
                    "rz": 24,
                    "measure": 18,
                    "sxdg": 10,
                    "rxx": 9,
                    "h": 9,
                    "sx": 7,
                    "rzz": 6,
                    "u3": 6,
                    "ryy": 5,
                    "rzx": 4,
                    "unitary": 3,
                    "u1": 1,
                    "barrier": 1
                }
            }
        },
        {
            "D": 12,
            "t": 36.0,
            "num_trotter_steps": 1,
            "circuit_time": "0:00:00.094533",
            "shot_processing": {
                "raw_unique_basis_states": 2947,
                "fermion_basis_rejected": 0,
                "kept_unique_basis_states": 2947,
                "fermion_shots_rejected": 0,
                "kept_shots": 10000
            },
            "new_basis_count": 629,
            "total_basis_count": 10789,
            "H_reduced_size": [
                10789,
                10789
            ],
            "reduction": 95.88432312011719,
            "H_reduced_e": 1.8845786070505661,
            "used_dense": false,
            "eigenvalue_time": "0:00:00.107341",
            "diff": 1.8848941171185547,
            "change_from_prev": 4.8173937237550035e-05,
            "circuit_cost": {
                "depth": 78,
                "size": 213,
                "num_2q_ops": 111,
                "count_ops": {
                    "cx": 84,
                    "u2": 27,
                    "rz": 24,
                    "measure": 18,
                    "sxdg": 10,
                    "rxx": 9,
                    "h": 9,
                    "sx": 7,
                    "rzz": 6,
                    "u3": 6,
                    "ryy": 5,
                    "rzx": 4,
                    "unitary": 3,
                    "u1": 1,
                    "barrier": 1
                }
            }
        },
        {
            "D": 13,
            "t": 39.0,
            "num_trotter_steps": 1,
            "circuit_time": "0:00:00.084746",
            "shot_processing": {
                "raw_unique_basis_states": 2232,
                "fermion_basis_rejected": 0,
                "kept_unique_basis_states": 2232,
                "fermion_shots_rejected": 0,
                "kept_shots": 10000
            },
            "new_basis_count": 308,
            "total_basis_count": 11097,
            "H_reduced_size": [
                11097,
                11097
            ],
            "reduction": 95.76683044433594,
            "H_reduced_e": 1.8844653845783226,
            "used_dense": false,
            "eigenvalue_time": "0:00:00.132238",
            "diff": 1.8847808946463112,
            "change_from_prev": 0.00011322247224354598,
            "circuit_cost": {
                "depth": 78,
                "size": 213,
                "num_2q_ops": 111,
                "count_ops": {
                    "cx": 84,
                    "u2": 27,
                    "rz": 24,
                    "measure": 18,
                    "sxdg": 10,
                    "rxx": 9,
                    "h": 9,
                    "sx": 7,
                    "rzz": 6,
                    "u3": 6,
                    "ryy": 5,
                    "rzx": 4,
                    "unitary": 3,
                    "u1": 1,
                    "barrier": 1
                }
            }
        },
        {
            "D": 14,
            "t": 42.0,
            "num_trotter_steps": 1,
            "circuit_time": "0:00:00.090617",
            "shot_processing": {
                "raw_unique_basis_states": 2290,
                "fermion_basis_rejected": 0,
                "kept_unique_basis_states": 2290,
                "fermion_shots_rejected": 0,
                "kept_shots": 10000
            },
            "new_basis_count": 327,
            "total_basis_count": 11424,
            "H_reduced_size": [
                11424,
                11424
            ],
            "reduction": 95.64208984375,
            "H_reduced_e": 1.8826132005353338,
            "used_dense": false,
            "eigenvalue_time": "0:00:00.134920",
            "diff": 1.8829287106033223,
            "change_from_prev": 0.0018521840429888137,
            "circuit_cost": {
                "depth": 78,
                "size": 213,
                "num_2q_ops": 111,
                "count_ops": {
                    "cx": 84,
                    "u2": 27,
                    "rz": 24,
                    "measure": 18,
                    "sxdg": 10,
                    "rxx": 9,
                    "h": 9,
                    "sx": 7,
                    "rzz": 6,
                    "u3": 6,
                    "ryy": 5,
                    "rzx": 4,
                    "unitary": 3,
                    "u1": 1,
                    "barrier": 1
                }
            }
        },
        {
            "D": 15,
            "t": 45.0,
            "num_trotter_steps": 1,
            "circuit_time": "0:00:00.093124",
            "shot_processing": {
                "raw_unique_basis_states": 3381,
                "fermion_basis_rejected": 0,
                "kept_unique_basis_states": 3381,
                "fermion_shots_rejected": 0,
                "kept_shots": 10000
            },
            "new_basis_count": 415,
            "total_basis_count": 11839,
            "H_reduced_size": [
                11839,
                11839
            ],
            "reduction": 95.48377990722656,
            "H_reduced_e": 1.8688124144402731,
            "used_dense": false,
            "eigenvalue_time": "0:00:00.144800",
            "diff": 1.8691279245082617,
            "change_from_prev": 0.013800786095060635,
            "circuit_cost": {
                "depth": 78,
                "size": 213,
                "num_2q_ops": 111,
                "count_ops": {
                    "cx": 84,
                    "u2": 27,
                    "rz": 24,
                    "measure": 18,
                    "sxdg": 10,
                    "rxx": 9,
                    "h": 9,
                    "sx": 7,
                    "rzz": 6,
                    "u3": 6,
                    "ryy": 5,
                    "rzx": 4,
                    "unitary": 3,
                    "u1": 1,
                    "barrier": 1
                }
            }
        },
        {
            "D": 16,
            "t": 48.0,
            "num_trotter_steps": 1,
            "circuit_time": "0:00:00.090435",
            "shot_processing": {
                "raw_unique_basis_states": 1893,
                "fermion_basis_rejected": 0,
                "kept_unique_basis_states": 1893,
                "fermion_shots_rejected": 0,
                "kept_shots": 10000
            },
            "new_basis_count": 181,
            "total_basis_count": 12020,
            "H_reduced_size": [
                12020,
                12020
            ],
            "reduction": 95.41473388671875,
            "H_reduced_e": 1.8687688579078503,
            "used_dense": false,
            "eigenvalue_time": "0:00:00.154376",
            "diff": 1.8690843679758389,
            "change_from_prev": 4.35565324228282e-05,
            "circuit_cost": {
                "depth": 78,
                "size": 213,
                "num_2q_ops": 111,
                "count_ops": {
                    "cx": 84,
                    "u2": 27,
                    "rz": 24,
                    "measure": 18,
                    "sxdg": 10,
                    "rxx": 9,
                    "h": 9,
                    "sx": 7,
                    "rzz": 6,
                    "u3": 6,
                    "ryy": 5,
                    "rzx": 4,
                    "unitary": 3,
                    "u1": 1,
                    "barrier": 1
                }
            }
        },
        {
            "D": 17,
            "t": 51.0,
            "num_trotter_steps": 1,
            "circuit_time": "0:00:00.093643",
            "shot_processing": {
                "raw_unique_basis_states": 1318,
                "fermion_basis_rejected": 0,
                "kept_unique_basis_states": 1318,
                "fermion_shots_rejected": 0,
                "kept_shots": 10000
            },
            "new_basis_count": 163,
            "total_basis_count": 12183,
            "H_reduced_size": [
                12183,
                12183
            ],
            "reduction": 95.35255432128906,
            "H_reduced_e": 0.0004861969553700674,
            "used_dense": false,
            "eigenvalue_time": "0:00:00.075585",
            "diff": 0.0008017070233585423,
            "change_from_prev": 1.8682826609524803,
            "circuit_cost": {
                "depth": 78,
                "size": 213,
                "num_2q_ops": 111,
                "count_ops": {
                    "cx": 84,
                    "u2": 27,
                    "rz": 24,
                    "measure": 18,
                    "sxdg": 10,
                    "rxx": 9,
                    "h": 9,
                    "sx": 7,
                    "rzz": 6,
                    "u3": 6,
                    "ryy": 5,
                    "rzx": 4,
                    "unitary": 3,
                    "u1": 1,
                    "barrier": 1
                }
            }
        },
        {
            "D": 18,
            "t": 54.0,
            "num_trotter_steps": 1,
            "circuit_time": "0:00:00.079851",
            "shot_processing": {
                "raw_unique_basis_states": 423,
                "fermion_basis_rejected": 0,
                "kept_unique_basis_states": 423,
                "fermion_shots_rejected": 0,
                "kept_shots": 10000
            },
            "new_basis_count": 15,
            "total_basis_count": 12198,
            "H_reduced_size": [
                12198,
                12198
            ],
            "reduction": 95.34683227539062,
            "H_reduced_e": 0.00048109424328956514,
            "used_dense": false,
            "eigenvalue_time": "0:00:00.093237",
            "diff": 0.0007966043112780401,
            "change_from_prev": 5.102712080502249e-06,
            "circuit_cost": {
                "depth": 78,
                "size": 213,
                "num_2q_ops": 111,
                "count_ops": {
                    "cx": 84,
                    "u2": 27,
                    "rz": 24,
                    "measure": 18,
                    "sxdg": 10,
                    "rxx": 9,
                    "h": 9,
                    "sx": 7,
                    "rzz": 6,
                    "u3": 6,
                    "ryy": 5,
                    "rzx": 4,
                    "unitary": 3,
                    "u1": 1,
                    "barrier": 1
                }
            }
        },
        {
            "D": 19,
            "t": 57.0,
            "num_trotter_steps": 1,
            "circuit_time": "0:00:00.094641",
            "shot_processing": {
                "raw_unique_basis_states": 2103,
                "fermion_basis_rejected": 0,
                "kept_unique_basis_states": 2103,
                "fermion_shots_rejected": 0,
                "kept_shots": 10000
            },
            "new_basis_count": 130,
            "total_basis_count": 12328,
            "H_reduced_size": [
                12328,
                12328
            ],
            "reduction": 95.2972412109375,
            "H_reduced_e": 0.00041574813931701324,
            "used_dense": false,
            "eigenvalue_time": "0:00:00.094820",
            "diff": 0.0007312582073054882,
            "change_from_prev": 6.53461039725519e-05,
            "circuit_cost": {
                "depth": 78,
                "size": 213,
                "num_2q_ops": 111,
                "count_ops": {
                    "cx": 84,
                    "u2": 27,
                    "rz": 24,
                    "measure": 18,
                    "sxdg": 10,
                    "rxx": 9,
                    "h": 9,
                    "sx": 7,
                    "rzz": 6,
                    "u3": 6,
                    "ryy": 5,
                    "rzx": 4,
                    "unitary": 3,
                    "u1": 1,
                    "barrier": 1
                }
            }
        },
        {
            "D": 20,
            "t": 60.0,
            "num_trotter_steps": 1,
            "circuit_time": "0:00:00.096318",
            "shot_processing": {
                "raw_unique_basis_states": 801,
                "fermion_basis_rejected": 0,
                "kept_unique_basis_states": 801,
                "fermion_shots_rejected": 0,
                "kept_shots": 10000
            },
            "new_basis_count": 5,
            "total_basis_count": 12333,
            "H_reduced_size": [
                12333,
                12333
            ],
            "reduction": 95.29533386230469,
            "H_reduced_e": 0.0004157481388868097,
            "used_dense": false,
            "eigenvalue_time": "0:00:00.093290",
            "diff": 0.0007312582068752847,
            "change_from_prev": 4.3020356157649764e-13,
            "circuit_cost": {
                "depth": 78,
                "size": 213,
                "num_2q_ops": 111,
                "count_ops": {
                    "cx": 84,
                    "u2": 27,
                    "rz": 24,
                    "measure": 18,
                    "sxdg": 10,
                    "rxx": 9,
                    "h": 9,
                    "sx": 7,
                    "rzz": 6,
                    "u3": 6,
                    "ryy": 5,
                    "rzx": 4,
                    "unitary": 3,
                    "u1": 1,
                    "barrier": 1
                }
            }
        },
        {
            "D": 21,
            "t": 31.5,
            "num_trotter_steps": 2,
            "circuit_time": "0:00:00.127236",
            "shot_processing": {
                "raw_unique_basis_states": 902,
                "fermion_basis_rejected": 0,
                "kept_unique_basis_states": 902,
                "fermion_shots_rejected": 0,
                "kept_shots": 10000
            },
            "new_basis_count": 235,
            "total_basis_count": 12568,
            "H_reduced_size": [
                12568,
                12568
            ],
            "reduction": 95.2056884765625,
            "H_reduced_e": 0.0003960738112787866,
            "used_dense": false,
            "eigenvalue_time": "0:00:00.106921",
            "diff": 0.0007115838792672617,
            "change_from_prev": 1.967432760802308e-05,
            "circuit_cost": {
                "depth": 155,
                "size": 408,
                "num_2q_ops": 222,
                "count_ops": {
                    "cx": 168,
                    "u2": 54,
                    "rz": 51,
                    "sxdg": 20,
                    "rxx": 18,
                    "h": 18,
                    "measure": 18,
                    "sx": 14,
                    "rzz": 12,
                    "ryy": 10,
                    "u3": 9,
                    "rzx": 8,
                    "unitary": 6,
                    "u1": 2,
                    "barrier": 1
                }
            }
        },
        {
            "D": 22,
            "t": 33.0,
            "num_trotter_steps": 2,
            "circuit_time": "0:00:00.126150",
            "shot_processing": {
                "raw_unique_basis_states": 3279,
                "fermion_basis_rejected": 0,
                "kept_unique_basis_states": 3279,
                "fermion_shots_rejected": 0,
                "kept_shots": 10000
            },
            "new_basis_count": 1401,
            "total_basis_count": 13969,
            "H_reduced_size": [
                13969,
                13969
            ],
            "reduction": 94.67124938964844,
            "H_reduced_e": 0.00019657793150924802,
            "used_dense": false,
            "eigenvalue_time": "0:00:00.133695",
            "diff": 0.000512087999497723,
            "change_from_prev": 0.00019949587976953858,
            "circuit_cost": {
                "depth": 155,
                "size": 408,
                "num_2q_ops": 222,
                "count_ops": {
                    "cx": 168,
                    "u2": 54,
                    "rz": 51,
                    "sxdg": 20,
                    "rxx": 18,
                    "h": 18,
                    "measure": 18,
                    "sx": 14,
                    "rzz": 12,
                    "ryy": 10,
                    "u3": 9,
                    "rzx": 8,
                    "unitary": 6,
                    "u1": 2,
                    "barrier": 1
                }
            }
        },
        {
            "D": 23,
            "t": 34.5,
            "num_trotter_steps": 2,
            "circuit_time": "0:00:00.123597",
            "shot_processing": {
                "raw_unique_basis_states": 2409,
                "fermion_basis_rejected": 0,
                "kept_unique_basis_states": 2409,
                "fermion_shots_rejected": 0,
                "kept_shots": 10000
            },
            "new_basis_count": 521,
            "total_basis_count": 14490,
            "H_reduced_size": [
                14490,
                14490
            ],
            "reduction": 94.47250366210938,
            "H_reduced_e": 0.00017261730302427697,
            "used_dense": false,
            "eigenvalue_time": "0:00:00.121651",
            "diff": 0.00048812737101275197,
            "change_from_prev": 2.396062848497105e-05,
            "circuit_cost": {
                "depth": 155,
                "size": 408,
                "num_2q_ops": 222,
                "count_ops": {
                    "cx": 168,
                    "u2": 54,
                    "rz": 51,
                    "sxdg": 20,
                    "rxx": 18,
                    "h": 18,
                    "measure": 18,
                    "sx": 14,
                    "rzz": 12,
                    "ryy": 10,
                    "u3": 9,
                    "rzx": 8,
                    "unitary": 6,
                    "u1": 2,
                    "barrier": 1
                }
            }
        },
        {
            "D": 24,
            "t": 36.0,
            "num_trotter_steps": 2,
            "circuit_time": "0:00:00.132390",
            "shot_processing": {
                "raw_unique_basis_states": 4421,
                "fermion_basis_rejected": 0,
                "kept_unique_basis_states": 4421,
                "fermion_shots_rejected": 0,
                "kept_shots": 10000
            },
            "new_basis_count": 207,
            "total_basis_count": 14697,
            "H_reduced_size": [
                14697,
                14697
            ],
            "reduction": 94.39353942871094,
            "H_reduced_e": -1.8364986328211006e-05,
            "used_dense": false,
            "eigenvalue_time": "0:00:00.133364",
            "diff": 0.000297145081660264,
            "change_from_prev": 0.00019098228935248798,
            "circuit_cost": {
                "depth": 155,
                "size": 408,
                "num_2q_ops": 222,
                "count_ops": {
                    "cx": 168,
                    "u2": 54,
                    "rz": 51,
                    "sxdg": 20,
                    "rxx": 18,
                    "h": 18,
                    "measure": 18,
                    "sx": 14,
                    "rzz": 12,
                    "ryy": 10,
                    "u3": 9,
                    "rzx": 8,
                    "unitary": 6,
                    "u1": 2,
                    "barrier": 1
                }
            }
        },
        {
            "D": 25,
            "t": 37.5,
            "num_trotter_steps": 2,
            "circuit_time": "0:00:00.130476",
            "shot_processing": {
                "raw_unique_basis_states": 1004,
                "fermion_basis_rejected": 0,
                "kept_unique_basis_states": 1004,
                "fermion_shots_rejected": 0,
                "kept_shots": 10000
            },
            "new_basis_count": 4,
            "total_basis_count": 14701,
            "H_reduced_size": [
                14701,
                14701
            ],
            "reduction": 94.39201354980469,
            "H_reduced_e": -1.8369163839683313e-05,
            "used_dense": false,
            "eigenvalue_time": "0:00:00.149379",
            "diff": 0.0002971409041487917,
            "change_from_prev": 4.177511472306576e-09,
            "circuit_cost": {
                "depth": 155,
                "size": 408,
                "num_2q_ops": 222,
                "count_ops": {
                    "cx": 168,
                    "u2": 54,
                    "rz": 51,
                    "sxdg": 20,
                    "rxx": 18,
                    "h": 18,
                    "measure": 18,
                    "sx": 14,
                    "rzz": 12,
                    "ryy": 10,
                    "u3": 9,
                    "rzx": 8,
                    "unitary": 6,
                    "u1": 2,
                    "barrier": 1
                }
            }
        },
        {
            "D": 26,
            "t": 39.0,
            "num_trotter_steps": 2,
            "circuit_time": "0:00:00.126816",
            "shot_processing": {
                "raw_unique_basis_states": 3101,
                "fermion_basis_rejected": 0,
                "kept_unique_basis_states": 3101,
                "fermion_shots_rejected": 0,
                "kept_shots": 10000
            },
            "new_basis_count": 82,
            "total_basis_count": 14783,
            "H_reduced_size": [
                14783,
                14783
            ],
            "reduction": 94.36073303222656,
            "H_reduced_e": -3.654533780810566e-05,
            "used_dense": false,
            "eigenvalue_time": "0:00:00.144521",
            "diff": 0.00027896473018036933,
            "change_from_prev": 1.817617396842235e-05,
            "circuit_cost": {
                "depth": 155,
                "size": 408,
                "num_2q_ops": 222,
                "count_ops": {
                    "cx": 168,
                    "u2": 54,
                    "rz": 51,
                    "sxdg": 20,
                    "rxx": 18,
                    "h": 18,
                    "measure": 18,
                    "sx": 14,
                    "rzz": 12,
                    "ryy": 10,
                    "u3": 9,
                    "rzx": 8,
                    "unitary": 6,
                    "u1": 2,
                    "barrier": 1
                }
            }
        },
        {
            "D": 27,
            "t": 40.5,
            "num_trotter_steps": 2,
            "circuit_time": "0:00:00.124669",
            "shot_processing": {
                "raw_unique_basis_states": 2190,
                "fermion_basis_rejected": 0,
                "kept_unique_basis_states": 2190,
                "fermion_shots_rejected": 0,
                "kept_shots": 10000
            },
            "new_basis_count": 249,
            "total_basis_count": 15032,
            "H_reduced_size": [
                15032,
                15032
            ],
            "reduction": 94.2657470703125,
            "H_reduced_e": -8.159613473273488e-05,
            "used_dense": false,
            "eigenvalue_time": "0:00:00.136076",
            "diff": 0.00023391393325574014,
            "change_from_prev": 4.505079692462922e-05,
            "circuit_cost": {
                "depth": 155,
                "size": 408,
                "num_2q_ops": 222,
                "count_ops": {
                    "cx": 168,
                    "u2": 54,
                    "rz": 51,
                    "sxdg": 20,
                    "rxx": 18,
                    "h": 18,
                    "measure": 18,
                    "sx": 14,
                    "rzz": 12,
                    "ryy": 10,
                    "u3": 9,
                    "rzx": 8,
                    "unitary": 6,
                    "u1": 2,
                    "barrier": 1
                }
            }
        },
        {
            "D": 28,
            "t": 42.0,
            "num_trotter_steps": 2,
            "circuit_time": "0:00:00.130188",
            "shot_processing": {
                "raw_unique_basis_states": 3440,
                "fermion_basis_rejected": 0,
                "kept_unique_basis_states": 3440,
                "fermion_shots_rejected": 0,
                "kept_shots": 10000
            },
            "new_basis_count": 735,
            "total_basis_count": 15767,
            "H_reduced_size": [
                15767,
                15767
            ],
            "reduction": 93.98536682128906,
            "H_reduced_e": -8.297720194293068e-05,
            "used_dense": false,
            "eigenvalue_time": "0:00:00.127085",
            "diff": 0.00023253286604554434,
            "change_from_prev": 1.3810672101958023e-06,
            "circuit_cost": {
                "depth": 155,
                "size": 408,
                "num_2q_ops": 222,
                "count_ops": {
                    "cx": 168,
                    "u2": 54,
                    "rz": 51,
                    "sxdg": 20,
                    "rxx": 18,
                    "h": 18,
                    "measure": 18,
                    "sx": 14,
                    "rzz": 12,
                    "ryy": 10,
                    "u3": 9,
                    "rzx": 8,
                    "unitary": 6,
                    "u1": 2,
                    "barrier": 1
                }
            }
        },
        {
            "D": 29,
            "t": 43.5,
            "num_trotter_steps": 2,
            "circuit_time": "0:00:00.126688",
            "shot_processing": {
                "raw_unique_basis_states": 1432,
                "fermion_basis_rejected": 0,
                "kept_unique_basis_states": 1432,
                "fermion_shots_rejected": 0,
                "kept_shots": 10000
            },
            "new_basis_count": 127,
            "total_basis_count": 15894,
            "H_reduced_size": [
                15894,
                15894
            ],
            "reduction": 93.93692016601562,
            "H_reduced_e": -8.454069044817711e-05,
            "used_dense": false,
            "eigenvalue_time": "0:00:00.137381",
            "diff": 0.00023096937754029788,
            "change_from_prev": 1.5634885052464252e-06,
            "circuit_cost": {
                "depth": 155,
                "size": 408,
                "num_2q_ops": 222,
                "count_ops": {
                    "cx": 168,
                    "u2": 54,
                    "rz": 51,
                    "sxdg": 20,
                    "rxx": 18,
                    "h": 18,
                    "measure": 18,
                    "sx": 14,
                    "rzz": 12,
                    "ryy": 10,
                    "u3": 9,
                    "rzx": 8,
                    "unitary": 6,
                    "u1": 2,
                    "barrier": 1
                }
            }
        },
        {
            "D": 30,
            "t": 45.0,
            "num_trotter_steps": 2,
            "circuit_time": "0:00:00.118643",
            "shot_processing": {
                "raw_unique_basis_states": 2632,
                "fermion_basis_rejected": 0,
                "kept_unique_basis_states": 2632,
                "fermion_shots_rejected": 0,
                "kept_shots": 10000
            },
            "new_basis_count": 344,
            "total_basis_count": 16238,
            "H_reduced_size": [
                16238,
                16238
            ],
            "reduction": 93.80569458007812,
            "H_reduced_e": -8.56039566550918e-05,
            "used_dense": false,
            "eigenvalue_time": "0:00:00.143204",
            "diff": 0.0002299061113333832,
            "change_from_prev": 1.0632662069146932e-06,
            "circuit_cost": {
                "depth": 155,
                "size": 408,
                "num_2q_ops": 222,
                "count_ops": {
                    "cx": 168,
                    "u2": 54,
                    "rz": 51,
                    "sxdg": 20,
                    "rxx": 18,
                    "h": 18,
                    "measure": 18,
                    "sx": 14,
                    "rzz": 12,
                    "ryy": 10,
                    "u3": 9,
                    "rzx": 8,
                    "unitary": 6,
                    "u1": 2,
                    "barrier": 1
                }
            }
        },
        {
            "D": 31,
            "t": 46.5,
            "num_trotter_steps": 2,
            "circuit_time": "0:00:00.131889",
            "shot_processing": {
                "raw_unique_basis_states": 3865,
                "fermion_basis_rejected": 0,
                "kept_unique_basis_states": 3865,
                "fermion_shots_rejected": 0,
                "kept_shots": 10000
            },
            "new_basis_count": 519,
            "total_basis_count": 16757,
            "H_reduced_size": [
                16757,
                16757
            ],
            "reduction": 93.60771179199219,
            "H_reduced_e": -9.061944502565356e-05,
            "used_dense": false,
            "eigenvalue_time": "0:00:00.121790",
            "diff": 0.00022489062296282146,
            "change_from_prev": 5.015488370561756e-06,
            "circuit_cost": {
                "depth": 155,
                "size": 408,
                "num_2q_ops": 222,
                "count_ops": {
                    "cx": 168,
                    "u2": 54,
                    "rz": 51,
                    "sxdg": 20,
                    "rxx": 18,
                    "h": 18,
                    "measure": 18,
                    "sx": 14,
                    "rzz": 12,
                    "ryy": 10,
                    "u3": 9,
                    "rzx": 8,
                    "unitary": 6,
                    "u1": 2,
                    "barrier": 1
                }
            }
        },
        {
            "D": 32,
            "t": 48.0,
            "num_trotter_steps": 2,
            "circuit_time": "0:00:00.118714",
            "shot_processing": {
                "raw_unique_basis_states": 2359,
                "fermion_basis_rejected": 0,
                "kept_unique_basis_states": 2359,
                "fermion_shots_rejected": 0,
                "kept_shots": 10000
            },
            "new_basis_count": 89,
            "total_basis_count": 16846,
            "H_reduced_size": [
                16846,
                16846
            ],
            "reduction": 93.57376098632812,
            "H_reduced_e": -9.090092553957398e-05,
            "used_dense": false,
            "eigenvalue_time": "0:00:00.160549",
            "diff": 0.00022460914244890103,
            "change_from_prev": 2.8148051392042127e-07,
            "circuit_cost": {
                "depth": 155,
                "size": 408,
                "num_2q_ops": 222,
                "count_ops": {
                    "cx": 168,
                    "u2": 54,
                    "rz": 51,
                    "sxdg": 20,
                    "rxx": 18,
                    "h": 18,
                    "measure": 18,
                    "sx": 14,
                    "rzz": 12,
                    "ryy": 10,
                    "u3": 9,
                    "rzx": 8,
                    "unitary": 6,
                    "u1": 2,
                    "barrier": 1
                }
            }
        },
        {
            "D": 33,
            "t": 49.5,
            "num_trotter_steps": 2,
            "circuit_time": "0:00:00.128218",
            "shot_processing": {
                "raw_unique_basis_states": 2207,
                "fermion_basis_rejected": 0,
                "kept_unique_basis_states": 2207,
                "fermion_shots_rejected": 0,
                "kept_shots": 10000
            },
            "new_basis_count": 18,
            "total_basis_count": 16864,
            "H_reduced_size": [
                16864,
                16864
            ],
            "reduction": 93.56689453125,
            "H_reduced_e": -9.254234796012244e-05,
            "used_dense": false,
            "eigenvalue_time": "0:00:00.146221",
            "diff": 0.00022296772002835256,
            "change_from_prev": 1.6414224205484577e-06,
            "circuit_cost": {
                "depth": 155,
                "size": 408,
                "num_2q_ops": 222,
                "count_ops": {
                    "cx": 168,
                    "u2": 54,
                    "rz": 51,
                    "sxdg": 20,
                    "rxx": 18,
                    "h": 18,
                    "measure": 18,
                    "sx": 14,
                    "rzz": 12,
                    "ryy": 10,
                    "u3": 9,
                    "rzx": 8,
                    "unitary": 6,
                    "u1": 2,
                    "barrier": 1
                }
            }
        },
        {
            "D": 34,
            "t": 51.0,
            "num_trotter_steps": 2,
            "circuit_time": "0:00:00.126649",
            "shot_processing": {
                "raw_unique_basis_states": 803,
                "fermion_basis_rejected": 0,
                "kept_unique_basis_states": 803,
                "fermion_shots_rejected": 0,
                "kept_shots": 10000
            },
            "new_basis_count": 0,
            "total_basis_count": 16864,
            "H_reduced_size": [
                16864,
                16864
            ],
            "reduction": 93.56689453125,
            "H_reduced_e": -9.25423479588011e-05,
            "used_dense": false,
            "eigenvalue_time": "0:00:00.147803",
            "diff": 0.0002229677200296739,
            "change_from_prev": 1.3213307401352403e-15,
            "circuit_cost": {
                "depth": 155,
                "size": 408,
                "num_2q_ops": 222,
                "count_ops": {
                    "cx": 168,
                    "u2": 54,
                    "rz": 51,
                    "sxdg": 20,
                    "rxx": 18,
                    "h": 18,
                    "measure": 18,
                    "sx": 14,
                    "rzz": 12,
                    "ryy": 10,
                    "u3": 9,
                    "rzx": 8,
                    "unitary": 6,
                    "u1": 2,
                    "barrier": 1
                }
            }
        },
        {
            "D": 35,
            "t": 35.0,
            "num_trotter_steps": 3,
            "circuit_time": "0:00:00.165161",
            "shot_processing": {
                "raw_unique_basis_states": 1304,
                "fermion_basis_rejected": 0,
                "kept_unique_basis_states": 1304,
                "fermion_shots_rejected": 0,
                "kept_shots": 10000
            },
            "new_basis_count": 90,
            "total_basis_count": 16954,
            "H_reduced_size": [
                16954,
                16954
            ],
            "reduction": 93.53256225585938,
            "H_reduced_e": -9.256699334212802e-05,
            "used_dense": false,
            "eigenvalue_time": "0:00:00.149728",
            "diff": 0.000222943074646347,
            "change_from_prev": 2.4645383326911234e-08,
            "circuit_cost": {
                "depth": 232,
                "size": 603,
                "num_2q_ops": 333,
                "count_ops": {
                    "cx": 252,
                    "u2": 81,
                    "rz": 78,
                    "sxdg": 30,
                    "rxx": 27,
                    "h": 27,
                    "sx": 21,
                    "rzz": 18,
                    "measure": 18,
                    "ryy": 15,
                    "u3": 12,
                    "rzx": 12,
                    "unitary": 9,
                    "u1": 3,
                    "barrier": 1
                }
            }
        },
        {
            "D": 36,
            "t": 36.0,
            "num_trotter_steps": 3,
            "circuit_time": "0:00:00.167646",
            "shot_processing": {
                "raw_unique_basis_states": 1891,
                "fermion_basis_rejected": 0,
                "kept_unique_basis_states": 1891,
                "fermion_shots_rejected": 0,
                "kept_shots": 10000
            },
            "new_basis_count": 42,
            "total_basis_count": 16996,
            "H_reduced_size": [
                16996,
                16996
            ],
            "reduction": 93.51654052734375,
            "H_reduced_e": -9.258797193002327e-05,
            "used_dense": false,
            "eigenvalue_time": "0:00:00.142279",
            "diff": 0.00022292209605845174,
            "change_from_prev": 2.0978587895250115e-08,
            "circuit_cost": {
                "depth": 232,
                "size": 603,
                "num_2q_ops": 333,
                "count_ops": {
                    "cx": 252,
                    "u2": 81,
                    "rz": 78,
                    "sxdg": 30,
                    "rxx": 27,
                    "h": 27,
                    "sx": 21,
                    "rzz": 18,
                    "measure": 18,
                    "ryy": 15,
                    "u3": 12,
                    "rzx": 12,
                    "unitary": 9,
                    "u1": 3,
                    "barrier": 1
                }
            }
        },
        {
            "D": 37,
            "t": 37.0,
            "num_trotter_steps": 3,
            "circuit_time": "0:00:00.156870",
            "shot_processing": {
                "raw_unique_basis_states": 1407,
                "fermion_basis_rejected": 0,
                "kept_unique_basis_states": 1407,
                "fermion_shots_rejected": 0,
                "kept_shots": 10000
            },
            "new_basis_count": 6,
            "total_basis_count": 17002,
            "H_reduced_size": [
                17002,
                17002
            ],
            "reduction": 93.51425170898438,
            "H_reduced_e": -9.258806017474453e-05,
            "used_dense": false,
            "eigenvalue_time": "0:00:00.158706",
            "diff": 0.00022292200781373048,
            "change_from_prev": 8.824472126330377e-11,
            "circuit_cost": {
                "depth": 232,
                "size": 603,
                "num_2q_ops": 333,
                "count_ops": {
                    "cx": 252,
                    "u2": 81,
                    "rz": 78,
                    "sxdg": 30,
                    "rxx": 27,
                    "h": 27,
                    "sx": 21,
                    "rzz": 18,
                    "measure": 18,
                    "ryy": 15,
                    "u3": 12,
                    "rzx": 12,
                    "unitary": 9,
                    "u1": 3,
                    "barrier": 1
                }
            }
        },
        {
            "D": 38,
            "t": 38.0,
            "num_trotter_steps": 3,
            "circuit_time": "0:00:00.166264",
            "shot_processing": {
                "raw_unique_basis_states": 642,
                "fermion_basis_rejected": 0,
                "kept_unique_basis_states": 642,
                "fermion_shots_rejected": 0,
                "kept_shots": 10000
            },
            "new_basis_count": 0,
            "total_basis_count": 17002,
            "H_reduced_size": [
                17002,
                17002
            ],
            "reduction": 93.51425170898438,
            "H_reduced_e": -9.258806016980463e-05,
            "used_dense": false,
            "eigenvalue_time": "0:00:00.173880",
            "diff": 0.00022292200781867037,
            "change_from_prev": 4.9398961483870796e-15,
            "circuit_cost": {
                "depth": 232,
                "size": 603,
                "num_2q_ops": 333,
                "count_ops": {
                    "cx": 252,
                    "u2": 81,
                    "rz": 78,
                    "sxdg": 30,
                    "rxx": 27,
                    "h": 27,
                    "sx": 21,
                    "rzz": 18,
                    "measure": 18,
                    "ryy": 15,
                    "u3": 12,
                    "rzx": 12,
                    "unitary": 9,
                    "u1": 3,
                    "barrier": 1
                }
            }
        }
    ],
    "num_jobs": null,
    "QPU_usage": null,
    "job_info": {},
    "sampler_options": {
        "backend_options": {
            "method": "automatic",
            "noise_model": null,
            "seed_simulator": 78201396
        },
        "run_options": {
            "shots": 10000
        }
    }
}