{
    "seed": 61737541,
    "starttime": "2026-01-19_18-22-56",
    "endtime": "2026-01-19_18-22-58",
    "time_taken": "0:00:01.461392",
    "H_info": {
        "potential": "linear",
        "boundary_condition": "dirichlet",
        "cutoff": 4,
        "N": 4,
        "a": 1.0,
        "c": null,
        "num_qubits": 12,
        "num_paulis": 59,
        "keep_ratio": 0.999,
        "trunc_info": {
            "m": 59,
            "n": 59,
            "keep_frac_terms": 1.0,
            "keep_ratio": 0.999,
            "truncated": 0.0,
            "total_weight": 55.40625
        },
        "dense_H_size": [
            4096,
            4096
        ],
        "eigenvalues": [
            -6.460202619787939e-05,
            0.898958757475228,
            0.8989587574752363,
            1.0278385676743689,
            1.0278385676743695,
            1.0465926975769329,
            1.046592697576938,
            1.259270831173729
        ],
        "basis": [
            0,
            0,
            0,
            0,
            0,
            1,
            0,
            0,
            0,
            0,
            0,
            1
        ]
    },
    "backend_info": {
        "backend_name": "Aer",
        "use_noise_model": 0,
        "noise_model_options": {
            "gate_error": true,
            "readout_error": true,
            "thermal_relaxation": true
        },
        "resilience_level": 2,
        "optimization_level": 3,
        "shots": 10000,
        "tags": [
            "NQCC-Q4",
            "SBQKD",
            "shots:10000",
            "dirichlet",
            "linear",
            "N=4",
            "cutoff=4"
        ]
    },
    "Ansatz_info": {
        "include_basis": true,
        "include_rys": true,
        "include_xxyys": true
    },
    "run_info": {
        "dt": 3.0,
        "max_k": 40,
        "tol": 1e-08,
        "conserve_fermion": true,
        "fermion_qubits": [
            2,
            5,
            8,
            11
        ],
        "num_fermions": 2,
        "trotter_patience": 2,
        "energy_patience": 3,
        "max_n_steps": 3
    },
    "final_k": 9,
    "converged": true,
    "all_energies": [
        0.00540265334901158,
        -5.489565331001258e-05,
        -6.22929912545218e-05,
        -6.229620486547387e-05,
        -6.343554328707207e-05,
        -6.345019163451579e-05,
        -6.34586409536578e-05,
        -6.345957703195664e-05,
        -6.345957702986446e-05
    ],
    "all_run_data": [
        {
            "D": 1,
            "t": 3.0,
            "num_trotter_steps": 1,
            "circuit_time": "0:00:00.032376",
            "shot_processing": {
                "raw_unique_basis_states": 339,
                "fermion_basis_rejected": 83,
                "kept_unique_basis_states": 256,
                "fermion_shots_rejected": 2138,
                "kept_shots": 7862
            },
            "new_basis_count": 256,
            "total_basis_count": 256,
            "H_reduced_size": [
                256,
                256
            ],
            "reduction": 93.75,
            "H_reduced_e": 0.00540265334901158,
            "used_dense": true,
            "eigenvalue_time": "0:00:00.033604",
            "diff": 0.00546725537520946,
            "change_from_prev": null,
            "circuit_cost": {
                "depth": 98,
                "size": 272,
                "num_2q_ops": 157,
                "count_ops": {
                    "cx": 132,
                    "u2": 38,
                    "rz": 30,
                    "h": 19,
                    "measure": 12,
                    "unitary": 10,
                    "rxx": 5,
                    "sxdg": 5,
                    "sx": 5,
                    "ry": 4,
                    "rzz": 4,
                    "rzx": 3,
                    "ryy": 3,
                    "u3": 2,
                    "barrier": 1
                }
            }
        },
        {
            "D": 2,
            "t": 6.0,
            "num_trotter_steps": 1,
            "circuit_time": "0:00:00.034047",
            "shot_processing": {
                "raw_unique_basis_states": 236,
                "fermion_basis_rejected": 21,
                "kept_unique_basis_states": 215,
                "fermion_shots_rejected": 27,
                "kept_shots": 9973
            },
            "new_basis_count": 76,
            "total_basis_count": 332,
            "H_reduced_size": [
                332,
                332
            ],
            "reduction": 91.89453125,
            "H_reduced_e": -5.489565331001258e-05,
            "used_dense": true,
            "eigenvalue_time": "0:00:00.057892",
            "diff": 9.706372887866802e-06,
            "change_from_prev": 0.005457549002321593,
            "circuit_cost": {
                "depth": 98,
                "size": 272,
                "num_2q_ops": 157,
                "count_ops": {
                    "cx": 132,
                    "u2": 38,
                    "rz": 30,
                    "h": 19,
                    "measure": 12,
                    "unitary": 10,
                    "rxx": 5,
                    "sxdg": 5,
                    "sx": 5,
                    "ry": 4,
                    "rzz": 4,
                    "rzx": 3,
                    "ryy": 3,
                    "u3": 2,
                    "barrier": 1
                }
            }
        },
        {
            "D": 3,
            "t": 9.0,
            "num_trotter_steps": 1,
            "circuit_time": "0:00:00.032440",
            "shot_processing": {
                "raw_unique_basis_states": 390,
                "fermion_basis_rejected": 98,
                "kept_unique_basis_states": 292,
                "fermion_shots_rejected": 4199,
                "kept_shots": 5801
            },
            "new_basis_count": 20,
            "total_basis_count": 352,
            "H_reduced_size": [
                352,
                352
            ],
            "reduction": 91.40625,
            "H_reduced_e": -6.22929912545218e-05,
            "used_dense": true,
            "eigenvalue_time": "0:00:00.068675",
            "diff": 2.3090349433575822e-06,
            "change_from_prev": 7.39733794450922e-06,
            "circuit_cost": {
                "depth": 98,
                "size": 272,
                "num_2q_ops": 157,
                "count_ops": {
                    "cx": 132,
                    "u2": 38,
                    "rz": 30,
                    "h": 19,
                    "measure": 12,
                    "unitary": 10,
                    "rxx": 5,
                    "sxdg": 5,
                    "sx": 5,
                    "ry": 4,
                    "rzz": 4,
                    "rzx": 3,
                    "ryy": 3,
                    "u3": 2,
                    "barrier": 1
                }
            }
        },
        {
            "D": 4,
            "t": 12.0,
            "num_trotter_steps": 1,
            "circuit_time": "0:00:00.035773",
            "shot_processing": {
                "raw_unique_basis_states": 197,
                "fermion_basis_rejected": 8,
                "kept_unique_basis_states": 189,
                "fermion_shots_rejected": 9,
                "kept_shots": 9991
            },
            "new_basis_count": 3,
            "total_basis_count": 355,
            "H_reduced_size": [
                355,
                355
            ],
            "reduction": 91.3330078125,
            "H_reduced_e": -6.229620486547387e-05,
            "used_dense": true,
            "eigenvalue_time": "0:00:00.070258",
            "diff": 2.3058213324055152e-06,
            "change_from_prev": 3.2136109520669977e-09,
            "circuit_cost": {
                "depth": 98,
                "size": 272,
                "num_2q_ops": 157,
                "count_ops": {
                    "cx": 132,
                    "u2": 38,
                    "rz": 30,
                    "h": 19,
                    "measure": 12,
                    "unitary": 10,
                    "rxx": 5,
                    "sxdg": 5,
                    "sx": 5,
                    "ry": 4,
                    "rzz": 4,
                    "rzx": 3,
                    "ryy": 3,
                    "u3": 2,
                    "barrier": 1
                }
            }
        },
        {
            "D": 5,
            "t": 15.0,
            "num_trotter_steps": 1,
            "circuit_time": "0:00:00.034050",
            "shot_processing": {
                "raw_unique_basis_states": 405,
                "fermion_basis_rejected": 86,
                "kept_unique_basis_states": 319,
                "fermion_shots_rejected": 1000,
                "kept_shots": 9000
            },
            "new_basis_count": 19,
            "total_basis_count": 374,
            "H_reduced_size": [
                374,
                374
            ],
            "reduction": 90.869140625,
            "H_reduced_e": -6.343554328707207e-05,
            "used_dense": true,
            "eigenvalue_time": "0:00:00.072902",
            "diff": 1.166482910807312e-06,
            "change_from_prev": 1.1393384215982032e-06,
            "circuit_cost": {
                "depth": 98,
                "size": 272,
                "num_2q_ops": 157,
                "count_ops": {
                    "cx": 132,
                    "u2": 38,
                    "rz": 30,
                    "h": 19,
                    "measure": 12,
                    "unitary": 10,
                    "rxx": 5,
                    "sxdg": 5,
                    "sx": 5,
                    "ry": 4,
                    "rzz": 4,
                    "rzx": 3,
                    "ryy": 3,
                    "u3": 2,
                    "barrier": 1
                }
            }
        },
        {
            "D": 6,
            "t": 18.0,
            "num_trotter_steps": 1,
            "circuit_time": "0:00:00.034466",
            "shot_processing": {
                "raw_unique_basis_states": 280,
                "fermion_basis_rejected": 39,
                "kept_unique_basis_states": 241,
                "fermion_shots_rejected": 113,
                "kept_shots": 9887
            },
            "new_basis_count": 1,
            "total_basis_count": 375,
            "H_reduced_size": [
                375,
                375
            ],
            "reduction": 90.8447265625,
            "H_reduced_e": -6.345019163451579e-05,
            "used_dense": true,
            "eigenvalue_time": "0:00:00.073594",
            "diff": 1.1518345633635964e-06,
            "change_from_prev": 1.4648347443715643e-08,
            "circuit_cost": {
                "depth": 98,
                "size": 272,
                "num_2q_ops": 157,
                "count_ops": {
                    "cx": 132,
                    "u2": 38,
                    "rz": 30,
                    "h": 19,
                    "measure": 12,
                    "unitary": 10,
                    "rxx": 5,
                    "sxdg": 5,
                    "sx": 5,
                    "ry": 4,
                    "rzz": 4,
                    "rzx": 3,
                    "ryy": 3,
                    "u3": 2,
                    "barrier": 1
                }
            }
        },
        {
            "D": 7,
            "t": 21.0,
            "num_trotter_steps": 1,
            "circuit_time": "0:00:00.032866",
            "shot_processing": {
                "raw_unique_basis_states": 356,
                "fermion_basis_rejected": 96,
                "kept_unique_basis_states": 260,
                "fermion_shots_rejected": 3702,
                "kept_shots": 6298
            },
            "new_basis_count": 2,
            "total_basis_count": 377,
            "H_reduced_size": [
                377,
                377
            ],
            "reduction": 90.7958984375,
            "H_reduced_e": -6.34586409536578e-05,
            "used_dense": true,
            "eigenvalue_time": "0:00:00.077018",
            "diff": 1.1433852442215865e-06,
            "change_from_prev": 8.449319142009803e-09,
            "circuit_cost": {
                "depth": 98,
                "size": 272,
                "num_2q_ops": 157,
                "count_ops": {
                    "cx": 132,
                    "u2": 38,
                    "rz": 30,
                    "h": 19,
                    "measure": 12,
                    "unitary": 10,
                    "rxx": 5,
                    "sxdg": 5,
                    "sx": 5,
                    "ry": 4,
                    "rzz": 4,
                    "rzx": 3,
                    "ryy": 3,
                    "u3": 2,
                    "barrier": 1
                }
            }
        },
        {
            "D": 8,
            "t": 12.0,
            "num_trotter_steps": 2,
            "circuit_time": "0:00:00.041170",
            "shot_processing": {
                "raw_unique_basis_states": 258,
                "fermion_basis_rejected": 38,
                "kept_unique_basis_states": 220,
                "fermion_shots_rejected": 64,
                "kept_shots": 9936
            },
            "new_basis_count": 1,
            "total_basis_count": 378,
            "H_reduced_size": [
                378,
                378
            ],
            "reduction": 90.771484375,
            "H_reduced_e": -6.345957703195664e-05,
            "used_dense": true,
            "eigenvalue_time": "0:00:00.078398",
            "diff": 1.1424491659227414e-06,
            "change_from_prev": 9.36078298845156e-10,
            "circuit_cost": {
                "depth": 194,
                "size": 529,
                "num_2q_ops": 311,
                "count_ops": {
                    "cx": 264,
                    "u2": 76,
                    "rz": 64,
                    "h": 38,
                    "unitary": 17,
                    "measure": 12,
                    "rxx": 10,
                    "sxdg": 10,
                    "sx": 10,
                    "rzz": 8,
                    "rzx": 6,
                    "ryy": 6,
                    "ry": 4,
                    "u3": 4,
                    "barrier": 1
                }
            }
        },
        {
            "D": 9,
            "t": 13.5,
            "num_trotter_steps": 2,
            "circuit_time": "0:00:00.041628",
            "shot_processing": {
                "raw_unique_basis_states": 288,
                "fermion_basis_rejected": 66,
                "kept_unique_basis_states": 222,
                "fermion_shots_rejected": 226,
                "kept_shots": 9774
            },
            "new_basis_count": 0,
            "total_basis_count": 378,
            "H_reduced_size": [
                378,
                378
            ],
            "reduction": 90.771484375,
            "H_reduced_e": -6.345957702986446e-05,
            "used_dense": true,
            "eigenvalue_time": "0:00:00.073706",
            "diff": 1.1424491680149263e-06,
            "change_from_prev": 2.092184932245278e-15,
            "circuit_cost": {
                "depth": 194,
                "size": 529,
                "num_2q_ops": 311,
                "count_ops": {
                    "cx": 264,
                    "u2": 76,
                    "rz": 64,
                    "h": 38,
                    "unitary": 17,
                    "measure": 12,
                    "rxx": 10,
                    "sxdg": 10,
                    "sx": 10,
                    "rzz": 8,
                    "rzx": 6,
                    "ryy": 6,
                    "ry": 4,
                    "u3": 4,
                    "barrier": 1
                }
            }
        }
    ],
    "num_jobs": null,
    "QPU_usage": null,
    "job_info": {},
    "sampler_options": {
        "backend_options": {
            "method": "automatic",
            "noise_model": null,
            "seed_simulator": 61737541
        },
        "run_options": {
            "shots": 10000
        }
    }
}